[
 {
  "name": " Sabeeh ul Hasan",
  "id": "HSO-3423-2023"
 },
 {
  "name": " Manzar sohail",
  "id": "F-1461-2014"
 },
 {
  "name": " zahid ahmed qureshi",
  "id": "HEU-3825-2022"
 },
 {
  "name": " asghari maqsood",
  "id": "F-3400-2015"
 },
 {
  "name": " adil malik",
  "id": "AAA-5528-2020"
 },
 {
  "name": " nadar khokhar",
  "id": "GPX-1699-2022"
 },
 {
  "name": " hassan Abdullah khalid",
  "id": "AAX-5108-2020"
 },
 {
  "name": " Aneela javed",
  "id": "ABE-8794-2021"
 },
 {
  "name": " sajjad hussain",
  "id": "AAE-2576-2019"
 },
 {
  "name": " Waleed bin Yousuf",
  "id": "EMG-6739-2022"
 },
 {
  "name": " sofia baig",
  "id": "X-7163-2019"
 },
 {
  "name": " Muhammad ali",
  "id": "HFZ-9322-2022"
 },
 {
  "name": " adeel akram",
  "id": "HGA-0692-2022"
 },
 {
  "name": " yasir ahmad",
  "id": "AAZ-7036-2020"
 },
 {
  "name": " Zeeshan Zulkifl",
  "id": "EHF-0039-2022"
 },
 {
  "name": " Syed Muhammad Ali Zuhaib",
  "id": "HPB-3159-2023"
 },
 {
  "name": " Muhammad Zuhaib",
  "id": "IIS-0243-2023"
 },
 {
  "name": " Muhammad Zubair",
  "id": "DSK-9464-2022"
 },
 {
  "name": " Ch. Muhammad Zubair",
  "id": "EIS-9463-2022"
 },
 {
  "name": " Mian MUhammad Zobair",
  "id": "J-1687-2014"
 },
 {
  "name": " Usman Zia",
  "id": "EIK-9887-2022"
 },
 {
  "name": " Saba Zia",
  "id": "HDO-2745-2022"
 },
 {
  "name": " Muhammad Danish Zia",
  "id": "DWI-0373-2022"
 },
 {
  "name": " Azka Zia",
  "id": "HMX-2096-2023"
 },
 {
  "name": " Adeel Zia",
  "id": "GLB-8267-2022"
 },
 {
  "name": " Dr Zeshan",
  "id": "HTN-2648-2023"
 },
 {
  "name": " Syeda Sundus Zehra",
  "id": "GBJ-9570-2022"
 },
 {
  "name": " Syeda Shafia Zehra",
  "id": "EIK-3443-2022"
 },
 {
  "name": " Muhammad Zeeshan",
  "id": "O-2147-2019"
 },
 {
  "name": " Muhammad Zeeshan",
  "id": "DXC-8210-2022"
 },
 {
  "name": " Muhammad Zeeshan",
  "id": "IQK-3876-2023"
 },
 {
  "name": " Uswa Zeb",
  "id": "GKD-0850-2022"
 },
 {
  "name": " Shah Zeb",
  "id": "AAH-3218-2021"
 },
 {
  "name": " Ayesha Zeb",
  "id": "HPF-3047-2023"
 },
 {
  "name": " Assist. Prof. Dr. Kamran Zeb",
  "id": "HMV-1556-2023"
 },
 {
  "name": " Syed Wahab Zarin",
  "id": "GJY-6681-2022"
 },
 {
  "name": " Abu Zar",
  "id": "GJY-7004-2022"
 },
 {
  "name": " Saira Zaniab",
  "id": "GJT-1233-2022"
 },
 {
  "name": " Roshan Zamir",
  "id": "HLG-5625-2023"
 },
 {
  "name": " Wajid Zaman",
  "id": "GRP-6679-2022"
 },
 {
  "name": " Uzair Khaleeq Uz Zaman",
  "id": "CHZ-5704-2022"
 },
 {
  "name": " Neelam Zaman",
  "id": "EHB-4356-2022"
 },
 {
  "name": " Gulmina Zaman Babar",
  "id": "DVB-1942-2022"
 },
 {
  "name": " Saira Zainab",
  "id": "AAE-3942-2022"
 },
 {
  "name": " Syed Muhammad Junaid Zaidi",
  "id": "GPK-7626-2022"
 },
 {
  "name": " Syed Mohammad Hassan Zaidi",
  "id": "GSB-9344-2022"
 },
 {
  "name": " Sajid Raza Zaidi",
  "id": "HHF-2234-2022"
 },
 {
  "name": " Najam Us Sahar Sadaf Zaidi",
  "id": "GLJ-1881-2022"
 },
 {
  "name": " Muhammad Zaid",
  "id": "GKK-8498-2022"
 },
 {
  "name": " Behzad Ahmed Zai",
  "id": "DZZ-2479-2022"
 },
 {
  "name": " Syedah Afsheen Zahra",
  "id": "DXJ-1111-2022"
 },
 {
  "name": " Rubab Zahra",
  "id": "CDF-3111-2022"
 },
 {
  "name": " Kainat Zahra",
  "id": "EIE-7370-2022"
 },
 {
  "name": " Musharaf Zahoor",
  "id": "EHJ-5798-2022"
 },
 {
  "name": " Hafiz Zahoor",
  "id": "B-4403-2018"
 },
 {
  "name": " H. Zahoor",
  "id": "DZN-7465-2022"
 },
 {
  "name": " Zeeshan Zahid",
  "id": "DZI-8235-2022"
 },
 {
  "name": " Zainab Zahid",
  "id": "EGQ-6755-2022"
 },
 {
  "name": " Saadia Zahid",
  "id": "GLA-8910-2022"
 },
 {
  "name": " Malik Sarmad Zahid",
  "id": "IIK-0453-2023"
 },
 {
  "name": " Herman Zahid",
  "id": "GMB-9096-2022"
 },
 {
  "name": " Hamza Zahid",
  "id": "DZL-2365-2022"
 },
 {
  "name": " Gulnaz Zahid",
  "id": "GFN-7007-2022"
 },
 {
  "name": " Ayesha Zaheer",
  "id": "EHK-7050-2022"
 },
 {
  "name": " Zuhair Zafar",
  "id": "DZA-6789-2022"
 },
 {
  "name": " Zeeshan Zafar",
  "id": "HRI-6354-2023"
 },
 {
  "name": " Syeda Maria Zafar",
  "id": "GLF-0680-2022"
 },
 {
  "name": " Sameen Zafar",
  "id": "HWP-9878-2023"
 },
 {
  "name": " Rizwan Zafar",
  "id": "EHP-2794-2022"
 },
 {
  "name": " Rana Inamullah Zafar",
  "id": "HHT-5844-2022"
 },
 {
  "name": " Nafey Zafar",
  "id": "EFP-8074-2022"
 },
 {
  "name": " Ibtesam Zafar",
  "id": "EIB-4620-2022"
 },
 {
  "name": " Adeel Zafar",
  "id": "FZP-5715-2022"
 },
 {
  "name": " Usman Zabit",
  "id": "W-4901-2018"
 },
 {
  "name": " Muhammad Yousif",
  "id": "C-3531-2019"
 },
 {
  "name": " Faisal Yousafzai",
  "id": "GKU-1580-2022"
 },
 {
  "name": " Tanzeela Yousaf",
  "id": "GKB-5446-2022"
 },
 {
  "name": " Raffia Bintay Yousaf",
  "id": "GKS-8088-2022"
 },
 {
  "name": " Muhammad Younis",
  "id": "CDI-3319-2022"
 },
 {
  "name": " Hassaan Bin Younis",
  "id": "CEM-5580-2022"
 },
 {
  "name": " Hamad Younis",
  "id": "GSA-4322-2022"
 },
 {
  "name": " Raheela Yasmin",
  "id": "GHN-9361-2022"
 },
 {
  "name": " Maria Yasmeen",
  "id": "CKL-9481-2022"
 },
 {
  "name": " Sana Yaqub",
  "id": "GYE-1948-2022"
 },
 {
  "name": " Tahreem Yaqoob",
  "id": "GKD-5889-2022"
 },
 {
  "name": " Lubna Yaqoob",
  "id": "GKH-4664-2022"
 },
 {
  "name": " Khurram Yaqoob",
  "id": "EGK-4661-2022"
 },
 {
  "name": " Khuram Yaqoob",
  "id": "HFX-8773-2022"
 },
 {
  "name": " Muhammad Yameen",
  "id": "HLN-3130-2023"
 },
 {
  "name": " Saad Wazir",
  "id": "ADA-9095-2022"
 },
 {
  "name": " Muhammad Adnan Waseem",
  "id": "EFW-4403-2022"
 },
 {
  "name": " Maaz Waseem",
  "id": "CGH-9954-2022"
 },
 {
  "name": " Hira Waris",
  "id": "EDZ-9196-2022"
 },
 {
  "name": " Asim Waris",
  "id": "AAD-5455-2020"
 },
 {
  "name": " Arfaa Waqas",
  "id": "GOU-5124-2022"
 },
 {
  "name": " Adeel Waqas",
  "id": "GEP-3275-2022"
 },
 {
  "name": " Adeel Waqas",
  "id": "N-8873-2013"
 },
 {
  "name": " Hira Waqar",
  "id": "GHD-1320-2022"
 },
 {
  "name": " Nauman Wajid",
  "id": "GWJ-3727-2022"
 },
 {
  "name": " Amtul Wadood Wajeeha",
  "id": "EDF-4921-2022"
 },
 {
  "name": " Maheen Wahid",
  "id": "HOQ-5305-2023"
 },
 {
  "name": " Sana Waheed",
  "id": "GIR-2018-2022"
 },
 {
  "name": " Palvasha Waheed",
  "id": "GIL-7609-2022"
 },
 {
  "name": " Arslan Waheed",
  "id": "GSI-5114-2022"
 },
 {
  "name": " Zujaja Wahaj",
  "id": "GFG-3446-2022"
 },
 {
  "name": " Maryam Wahab",
  "id": "AEJ-4073-2022"
 },
 {
  "name": " Abdul Malek Abdul Wahab",
  "id": "FZH-4037-2022"
 },
 {
  "name": " Fehmida Usmani",
  "id": "DZD-5337-2022"
 },
 {
  "name": " Muhammad Usman",
  "id": "I-1607-2019"
 },
 {
  "name": " Muhammad Usman",
  "id": "H-8148-2015"
 },
 {
  "name": " Muhammad Usman",
  "id": "HJV-3807-2023"
 },
 {
  "name": " Muhammad Usman",
  "id": "ABB-4563-2020"
 },
 {
  "name": " Javaid Usman",
  "id": "EDF-2532-2022"
 },
 {
  "name": " Hafiz Muhammad Ushamah",
  "id": "GYZ-2001-2022"
 },
 {
  "name": " Muhammad Usama",
  "id": "ABG-9525-2020"
 },
 {
  "name": " Sidra Urooj",
  "id": "HKQ-1316-2023"
 },
 {
  "name": " Fatima Urooj",
  "id": "EDF-6518-2022"
 },
 {
  "name": " Hamood Ur Rahman",
  "id": "ABE-4601-2021"
 },
 {
  "name": " Malik Adeel Umer",
  "id": "GEI-1830-2022"
 },
 {
  "name": " Muhammad Umar",
  "id": "IIJ-8166-2023"
 },
 {
  "name": " Najam Ulqadir",
  "id": "EAQ-6576-2022"
 },
 {
  "name": " kafait Ullah",
  "id": "AAI-5856-2020"
 },
 {
  "name": " Zahid Ullah",
  "id": "HQX-4669-2023"
 },
 {
  "name": " Sidra Rahmat Ullah",
  "id": "FYN-8462-2022"
 },
 {
  "name": " Sharif Ullah",
  "id": "GHC-1310-2022"
 },
 {
  "name": " Qareeb Ullah",
  "id": "HQV-3462-2023"
 },
 {
  "name": " Maryam Ezat Ullah",
  "id": "EAL-5032-2022"
 },
 {
  "name": " Kafait Ullah",
  "id": "GPV-5677-2022"
 },
 {
  "name": " Imran Ullah",
  "id": "HHD-3325-2022"
 },
 {
  "name": " Imran Ullah",
  "id": "HMG-1117-2023"
 },
 {
  "name": " Hidayat Ullah",
  "id": "FZS-0017-2022"
 },
 {
  "name": " Haji Sami Ullah",
  "id": "HWJ-9703-2023"
 },
 {
  "name": " Hafeez Ullah",
  "id": "HLM-5966-2023"
 },
 {
  "name": " Habib Ullah",
  "id": "GYV-9652-2022"
 },
 {
  "name": " Farhan Ullah",
  "id": "DUW-5930-2022"
 },
 {
  "name": " Arshad Ullah",
  "id": "AAV-5650-2021"
 },
 {
  "name": " Abasin Ulasyar",
  "id": "GZA-8522-2022"
 },
 {
  "name": " Tanweer Ul Islam",
  "id": "ECA-9182-2022"
 },
 {
  "name": " Taimoor Ul Islam",
  "id": "HQL-1902-2023"
 },
 {
  "name": " Tauqeer Ul Islaam",
  "id": "HMK-0062-2023"
 },
 {
  "name": " Sumara Masood Ul Hassan",
  "id": "CDA-7519-2022"
 },
 {
  "name": " Amin Ul Hasnat",
  "id": "CHY-6393-2022"
 },
 {
  "name": " Zeeshan Ul Haq",
  "id": "GGB-1308-2022"
 },
 {
  "name": " U. Ul Haq",
  "id": "GIJ-8726-2022"
 },
 {
  "name": " Sheikh Ehsan Ul Haq",
  "id": "EAW-8019-2022"
 },
 {
  "name": " Ahtsham Ul Haq",
  "id": "GIM-7960-2022"
 },
 {
  "name": " Muhammad Ashar Ul Aleem",
  "id": "GGL-1588-2022"
 },
 {
  "name": " Ali Zain Ul Abadeen",
  "id": "GMB-6524-2022"
 },
 {
  "name": " Emad Uddin",
  "id": "I-5737-2015"
 },
 {
  "name": " Imran Touqir",
  "id": "GJF-7719-2022"
 },
 {
  "name": " Mohsin I. Tiwana",
  "id": "GJG-3160-2022"
 },
 {
  "name": " Nadia Tayyab",
  "id": "DZZ-5111-2022"
 },
 {
  "name": " M. Tauseef",
  "id": "GEH-8523-2022"
 },
 {
  "name": " Mariya Tauqeer",
  "id": "HDY-8601-2022"
 },
 {
  "name": " Saman Taufiq",
  "id": "GMB-3488-2022"
 },
 {
  "name": " Ufaq Tasneem",
  "id": "GFY-9795-2022"
 },
 {
  "name": " Sunila Tasfeen",
  "id": "HPA-7234-2023"
 },
 {
  "name": " Zarrar Tariq",
  "id": "GZK-0062-2022"
 },
 {
  "name": " S. Tariq",
  "id": "HJB-6640-2022"
 },
 {
  "name": " Rimsha Tariq",
  "id": "CFM-4136-2022"
 },
 {
  "name": " Muhammad Ali Tariq",
  "id": "GVY-0567-2022"
 },
 {
  "name": " Momna Tariq",
  "id": "CGH-1072-2022"
 },
 {
  "name": " Moiz Tariq",
  "id": "DZU-8066-2022"
 },
 {
  "name": " Farina Tariq",
  "id": "HOQ-4747-2023"
 },
 {
  "name": " Bazil Tariq",
  "id": "GRD-1776-2022"
 },
 {
  "name": " Anum Tariq",
  "id": "FZL-7779-2022"
 },
 {
  "name": " Adeel Tariq",
  "id": "N-7074-2018"
 },
 {
  "name": " Tahreem Tanweer",
  "id": "ECW-1772-2022"
 },
 {
  "name": " Muhammad Tanvir",
  "id": "HII-1613-2022"
 },
 {
  "name": " Waqas Tanveer",
  "id": "AAS-5374-2021"
 },
 {
  "name": " Syed Muhammad Umar Talha",
  "id": "ECK-3422-2022"
 },
 {
  "name": " Saadia Talay",
  "id": "DZJ-8112-2022"
 },
 {
  "name": " Hassan Talat",
  "id": "DYH-9964-2022"
 },
 {
  "name": " Nayab Tajved",
  "id": "GMV-6425-2022"
 },
 {
  "name": " Souad Taj",
  "id": "HKK-6322-2023"
 },
 {
  "name": " Safia Taj",
  "id": "HMO-5111-2023"
 },
 {
  "name": " Muhammad Ali Taimoor",
  "id": "IGU-8369-2023"
 },
 {
  "name": " Syeda Duaa Tahir",
  "id": "EBC-8289-2022"
 },
 {
  "name": " Shayan Tahir",
  "id": "GPD-7754-2022"
 },
 {
  "name": " Shahzaib Tahir",
  "id": "GHS-6779-2022"
 },
 {
  "name": " R. Tahir",
  "id": "CCB-4157-2022"
 },
 {
  "name": " Muhammad Tahir",
  "id": "AAA-3137-2020"
 },
 {
  "name": " Hasan Tahir",
  "id": "GCU-3951-2022"
 },
 {
  "name": " Farooq Ahmad Tahir",
  "id": "G-9800-2016"
 },
 {
  "name": " Arsalan Tahir",
  "id": "GGK-2798-2022"
 },
 {
  "name": " Ali Tahir",
  "id": "GYB-6008-2022"
 },
 {
  "name": " S TAHIRA",
  "id": "CDJ-0149-2022"
 },
 {
  "name": " Zain Syed",
  "id": "ECE-6133-2022"
 },
 {
  "name": " Kamran Naveed Syed",
  "id": "GYN-1412-2022"
 },
 {
  "name": " Samina Sundus",
  "id": "HSO-1396-2023"
 },
 {
  "name": " Sumera",
  "id": "GHX-2131-2022"
 },
 {
  "name": " Neha Sultan",
  "id": "GMU-1004-2022"
 },
 {
  "name": " Hajrah Sultan",
  "id": "GQV-3409-2022"
 },
 {
  "name": " Asim Sultan",
  "id": "DZO-9494-2022"
 },
 {
  "name": " Ali Bin Mazhar Sultan",
  "id": "IQJ-6316-2023"
 },
 {
  "name": " Aiman Sultan",
  "id": "CEG-1223-2022"
 },
 {
  "name": " Bilal Sulaman",
  "id": "CEK-5631-2022"
 },
 {
  "name": " Abu Sufyan",
  "id": "HLG-0076-2023"
 },
 {
  "name": " Ahmad Rauf Subhani",
  "id": "ABC-8653-2020"
 },
 {
  "name": " Noor Us Subah",
  "id": "IQJ-9028-2023"
 },
 {
  "name": " Sumair Ahmed Soomro",
  "id": "HWA-7409-2023"
 },
 {
  "name": " Umair Sohail",
  "id": "DSS-4702-2022"
 },
 {
  "name": " Nabia Farrukh Sohail",
  "id": "DTX-7307-2022"
 },
 {
  "name": " Manzar Sohail",
  "id": "GMW-6460-2022"
 },
 {
  "name": " Mehreen Sirshar",
  "id": "DSA-9686-2022"
 },
 {
  "name": " Umair Sikander",
  "id": "FVP-7196-2022"
 },
 {
  "name": " Laila Sikander",
  "id": "GLZ-9469-2022"
 },
 {
  "name": " Syed Ahmad Siffat",
  "id": "GBQ-3952-2022"
 },
 {
  "name": " Salma Siddiqui",
  "id": "DQU-1088-2022"
 },
 {
  "name": " Muhammad Israr Siddiqui",
  "id": "DRI-0649-2022"
 },
 {
  "name": " Ayesha S. Siddiqui",
  "id": "FYA-1350-2022"
 },
 {
  "name": " Asra Abid Siddiqui",
  "id": "HIQ-0036-2022"
 },
 {
  "name": " Adil Masood Siddiqui",
  "id": "FUY-3135-2022"
 },
 {
  "name": " Zahid Siddique",
  "id": "DTN-2567-2022"
 },
 {
  "name": " Muhammad Zahid Siddique",
  "id": "FWG-9781-2022"
 },
 {
  "name": " Muhammad Shahid Siddique",
  "id": "FZT-7551-2022"
 },
 {
  "name": " Abubakar Siddique",
  "id": "HNV-6078-2023"
 },
 {
  "name": " Rafiya Sibtain",
  "id": "GMN-5446-2022"
 },
 {
  "name": " Adnan Shujah",
  "id": "DRN-5367-2022"
 },
 {
  "name": " Iram Showkat",
  "id": "GPN-8046-2022"
 },
 {
  "name": " Nosherwan Shoaib",
  "id": "DXK-6405-2022"
 },
 {
  "name": " Samreen Sheriff",
  "id": "GCF-6640-2022"
 },
 {
  "name": " Ahmad Muqeem Sheri",
  "id": "GBQ-7641-2022"
 },
 {
  "name": " Muhammad Abid Sherazi",
  "id": "DQL-9365-2022"
 },
 {
  "name": " Noreen SherAkbar",
  "id": "DRV-0721-2022"
 },
 {
  "name": " Zaryab Sheikh",
  "id": "GEW-5735-2022"
 },
 {
  "name": " Shahzad Amin Sheikh",
  "id": "P-3985-2015"
 },
 {
  "name": " Nadia Shehzad",
  "id": "GWX-9633-2022"
 },
 {
  "name": " Adeeb Shehzad",
  "id": "HHN-4847-2022"
 },
 {
  "name": " Muhammad Sheheryar",
  "id": "HJO-2936-2023"
 },
 {
  "name": " Muhammad Khuram Shazhad",
  "id": "A-9576-2016"
 },
 {
  "name": " Bakhtawar Shaukat",
  "id": "HDC-3517-2022"
 },
 {
  "name": " Arsalan Shaukat",
  "id": "GDX-9058-2022"
 },
 {
  "name": " Muhammad Shariq",
  "id": "DQL-8148-2022"
 },
 {
  "name": " Marium Sharif",
  "id": "HMK-3216-2023"
 },
 {
  "name": " M. N. Sharif",
  "id": "GWE-2305-2022"
 },
 {
  "name": " Taimur Ali Shams",
  "id": "ABC-5549-2020"
 },
 {
  "name": " Moniba Shams",
  "id": "DSN-8066-2022"
 },
 {
  "name": " Moniba Shams",
  "id": "AAE-7386-2019"
 },
 {
  "name": " Sehar Shakir",
  "id": "FWD-5406-2022"
 },
 {
  "name": " Sarmad Shakeel",
  "id": "O-8200-2019"
 },
 {
  "name": " Zainab Shahzad",
  "id": "DPT-6887-2022"
 },
 {
  "name": " Naeem Shahzad",
  "id": "G-8091-2015"
 },
 {
  "name": " Nadia Shahzad",
  "id": "HYN-4105-2023"
 },
 {
  "name": " Muhammad Shahzad",
  "id": "GYH-0894-2022"
 },
 {
  "name": " Kashif Shahzad",
  "id": "GDQ-1466-2022"
 },
 {
  "name": " Hafiz Muhammad Aamir Shahzad",
  "id": "AAR-5670-2021"
 },
 {
  "name": " Gul Shahzad",
  "id": "DQY-9810-2022"
 },
 {
  "name": " Ahsan Shahzad",
  "id": "K-4985-2019"
 },
 {
  "name": " Adil Ahmad Shahzad",
  "id": "HVL-0144-2023"
 },
 {
  "name": " Aamer Shahzad",
  "id": "AAE-4394-2020"
 },
 {
  "name": " A. Shahzad",
  "id": "DSV-5836-2022"
 },
 {
  "name": " Muhammad Usman Shahid",
  "id": "FWP-3997-2022"
 },
 {
  "name": " Muhammad Shahid",
  "id": "DRX-6836-2022"
 },
 {
  "name": " Muhammad Shahid",
  "id": "IGK-7604-2023"
 },
 {
  "name": " Muhammad Shahid",
  "id": "FWE-4974-2022"
 },
 {
  "name": " Muhammad Shahid",
  "id": "DVC-7852-2022"
 },
 {
  "name": " Muhammad Shahid",
  "id": "I-6227-2018"
 },
 {
  "name": " Maheen Shahid",
  "id": "DQR-1915-2022"
 },
 {
  "name": " M. Shahid",
  "id": "FZD-1615-2022"
 },
 {
  "name": " M. Shahid",
  "id": "DTE-2501-2022"
 },
 {
  "name": " Kanza Shahid",
  "id": "GZI-2475-2022"
 },
 {
  "name": " Jahanzeb Shahid",
  "id": "GGP-2189-2022"
 },
 {
  "name": " Ameen Shahid",
  "id": "HHL-3083-2022"
 },
 {
  "name": " Aamna Shahid",
  "id": "FWA-0169-2022"
 },
 {
  "name": " K Shaheen",
  "id": "DRB-3170-2022"
 },
 {
  "name": " Tajammul Shah",
  "id": "GLZ-3860-2022"
 },
 {
  "name": " Syeda Saba Shah",
  "id": "FXX-5837-2022"
 },
 {
  "name": " Syeda Anmol Saba Shah",
  "id": "FWP-3270-2022"
 },
 {
  "name": " Syed Waiz Shah",
  "id": "FVT-3294-2022"
 },
 {
  "name": " Syed Tayyab Hussain Shah",
  "id": "E-4541-2016"
 },
 {
  "name": " Syed Shoaib Ahmad Shah",
  "id": "F-1862-2016"
 },
 {
  "name": " Syed Sarmad Shah",
  "id": "DUC-4669-2022"
 },
 {
  "name": " Syed Aqueel Shah",
  "id": "HFH-4757-2022"
 },
 {
  "name": " S. I. Shah",
  "id": "GVY-3946-2022"
 },
 {
  "name": " Mohammad Uzair Shah",
  "id": "HZF-0554-2023"
 },
 {
  "name": " Mati Ullah Shah",
  "id": "GNP-7920-2022"
 },
 {
  "name": " M. A. K. Yousaf Shah",
  "id": "GPZ-5776-2022"
 },
 {
  "name": " Imran Shah",
  "id": "AAN-8606-2020"
 },
 {
  "name": " Hassan Jalil Shah",
  "id": "DQG-7814-2022"
 },
 {
  "name": " Hania Shah",
  "id": "FVL-8602-2022"
 },
 {
  "name": " Aqueel Shah",
  "id": "GRM-6134-2022"
 },
 {
  "name": " Abid Shah",
  "id": "FWC-2048-2022"
 },
 {
  "name": " A. Shah",
  "id": "GMI-2823-2022"
 },
 {
  "name": " Narmeen Shafqat",
  "id": "HQU-3756-2023"
 },
 {
  "name": " Iqra Shafique",
  "id": "FVP-5519-2022"
 },
 {
  "name": " Dania Shafique",
  "id": "HNG-0836-2023"
 },
 {
  "name": " Unsub Shafiq",
  "id": "FVD-9057-2022"
 },
 {
  "name": " U. Shafiq",
  "id": "DSI-6265-2022"
 },
 {
  "name": " Uferah Shafi",
  "id": "DYP-8775-2022"
 },
 {
  "name": " Imran Shafi",
  "id": "DYY-3405-2022"
 },
 {
  "name": " Zunaira Shafaq",
  "id": "DPV-5545-2022"
 },
 {
  "name": " Balawal Shabir",
  "id": "AAF-2223-2020"
 },
 {
  "name": " Maria Shabbir",
  "id": "AAA-5414-2019"
 },
 {
  "name": " A. Shabbir",
  "id": "HFZ-7167-2022"
 },
 {
  "name": " Bakhtawar Sehar",
  "id": "GYZ-9526-2022"
 },
 {
  "name": " Aamir Naseem Satti",
  "id": "FWE-2274-2022"
 },
 {
  "name": " Naukhez Sarwar",
  "id": "DPC-7535-2022"
 },
 {
  "name": " Qassam Sarmad",
  "id": "DQI-5239-2022"
 },
 {
  "name": " Maria Binte Sarfraz",
  "id": "IPC-5890-2023"
 },
 {
  "name": " Hassan Sardar",
  "id": "FXV-7894-2022"
 },
 {
  "name": " Zunaira Saqib",
  "id": "FVZ-1229-2022"
 },
 {
  "name": " Najam Us Saqib",
  "id": "FZA-5642-2022"
 },
 {
  "name": " Maaza Sana",
  "id": "GMG-4549-2022"
 },
 {
  "name": " S. E. Samma",
  "id": "FWG-0010-2022"
 },
 {
  "name": " Samia",
  "id": "FWF-5168-2022"
 },
 {
  "name": " Fatima Samea",
  "id": "DRN-1200-2022"
 },
 {
  "name": " Abdul Samad",
  "id": "GUP-3676-2022"
 },
 {
  "name": " Verda Salman",
  "id": "ABC-7615-2020"
 },
 {
  "name": " Muhammad Salman Khan",
  "id": "HHP-1795-2022"
 },
 {
  "name": " Amber Salim",
  "id": "GOQ-1683-2022"
 },
 {
  "name": " Shahzad Saleem",
  "id": "FXZ-1840-2022"
 },
 {
  "name": " Muhammad Mubasher Saleem",
  "id": "AAI-2540-2019"
 },
 {
  "name": " Muhammad Farhan Saleem",
  "id": "DRF-2089-2022"
 },
 {
  "name": " Muhammad Saleem",
  "id": "IGB-8659-2023"
 },
 {
  "name": " Mohsin Saleem",
  "id": "DPM-9889-2022"
 },
 {
  "name": " Mohsin Saleem",
  "id": "DTU-9146-2022"
 },
 {
  "name": " M. R. Saleem",
  "id": "HJJ-8395-2023"
 },
 {
  "name": " Anum Abdul Salam",
  "id": "DPJ-1463-2022"
 },
 {
  "name": " Abdul Salam",
  "id": "HJR-2104-2023"
 },
 {
  "name": " Zarrar Salahuddin",
  "id": "ABA-2438-2020"
 },
 {
  "name": " Zunaira Sajjad",
  "id": "DPL-0380-2022"
 },
 {
  "name": " Zubair Sajid",
  "id": "GBN-9102-2022"
 },
 {
  "name": " Umair Sajid",
  "id": "FXK-1405-2022"
 },
 {
  "name": " Muhammad Tanveer Sajid",
  "id": "DYS-2193-2022"
 },
 {
  "name": " Muhammad Bilal Sajid",
  "id": "GQH-8124-2022"
 },
 {
  "name": " Muhammad Sajid",
  "id": "B-5313-2013"
 },
 {
  "name": " Masooma Sajid",
  "id": "FVB-5846-2022"
 },
 {
  "name": " Jamsheed Sajid",
  "id": "GMO-5062-2022"
 },
 {
  "name": " Hassan Sajid",
  "id": "DRB-3918-2022"
 },
 {
  "name": " Hasan Sajid",
  "id": "FTI-3022-2022"
 },
 {
  "name": " Hafiz Muhammad Sajid",
  "id": "FTW-3273-2022"
 },
 {
  "name": " Rai Sajjad Saif",
  "id": "FTP-3747-2022"
 },
 {
  "name": " Irfan Sahibzada",
  "id": "AID-9947-2022"
 },
 {
  "name": " Saria Safdar",
  "id": "FSB-5883-2022"
 },
 {
  "name": " Nabeel Safdar",
  "id": "AAZ-4803-2021"
 },
 {
  "name": " Fasiha Safdar",
  "id": "GEO-9615-2022"
 },
 {
  "name": " Amna Safdar",
  "id": "IAN-4427-2023"
 },
 {
  "name": " Umer Saeed",
  "id": "DWX-9800-2022"
 },
 {
  "name": " Ramsha Saeed",
  "id": "DRL-8487-2022"
 },
 {
  "name": " Anjum Saeed",
  "id": "FVE-0268-2022"
 },
 {
  "name": " Shazia Sadiq",
  "id": "CBV-9062-2022"
 },
 {
  "name": " Ayesha Sadiq",
  "id": "FUO-4640-2022"
 },
 {
  "name": " Hina Sadaf",
  "id": "DNX-7459-2022"
 },
 {
  "name": " S. Sabir",
  "id": "FXR-1003-2022"
 },
 {
  "name": " Muhammad Sabir",
  "id": "AAE-7923-2019"
 },
 {
  "name": " Ahsan Saadat",
  "id": "FWI-7049-2022"
 },
 {
  "name": " Muhammad Saad",
  "id": "GYD-0181-2022"
 },
 {
  "name": " Muhammad Saad",
  "id": "HEA-4415-2022"
 },
 {
  "name": " Muhammad Saad",
  "id": "GYD-0366-2022"
 },
 {
  "name": " H. M. Saad",
  "id": "GUP-2169-2022"
 },
 {
  "name": " MUHAMMAD SAEED",
  "id": "GSI-9323-2022"
 },
 {
  "name": " A. S. Rukh",
  "id": "DQP-6578-2022"
 },
 {
  "name": " Saddaf Rubab",
  "id": "AGN-0537-2022"
 },
 {
  "name": " N. Rubab",
  "id": "DPL-1986-2022"
 },
 {
  "name": " Joveria Rubab",
  "id": "HNF-2913-2023"
 },
 {
  "name": " Anosha Rubab",
  "id": "DQB-7649-2022"
 },
 {
  "name": " Mah Roosh",
  "id": "GWT-9911-2022"
 },
 {
  "name": " Syed Rizwan",
  "id": "AAF-1182-2019"
 },
 {
  "name": " Muhammad Suhail Rizwan",
  "id": "ADQ-2615-2022"
 },
 {
  "name": " Muhammad Rizwan",
  "id": "GAF-1745-2022"
 },
 {
  "name": " Areeb Rizwan",
  "id": "FTW-1233-2022"
 },
 {
  "name": " Syed Khurram Jah Rizvi",
  "id": "FUF-2814-2022"
 },
 {
  "name": " Sohaib Riaz",
  "id": "FTC-3700-2022"
 },
 {
  "name": " Ramish Riaz",
  "id": "O-6891-2017"
 },
 {
  "name": " R. Riaz",
  "id": "GEZ-6430-2022"
 },
 {
  "name": " Qaiser Riaz",
  "id": "AEZ-4665-2022"
 },
 {
  "name": " Nida Riaz",
  "id": "DNU-4974-2022"
 },
 {
  "name": " Hassan Riaz",
  "id": "FTU-7426-2022"
 },
 {
  "name": " Farhan Riaz",
  "id": "AAR-8628-2020"
 },
 {
  "name": " Muhammad Reshaeel",
  "id": "DPA-8523-2022"
 },
 {
  "name": " Shafi Rehman",
  "id": "GOE-1356-2022"
 },
 {
  "name": " Mujeeb ur Rehman",
  "id": "ABB-1072-2021"
 },
 {
  "name": " Mujeeb Rehman",
  "id": "AAE-7374-2019"
 },
 {
  "name": " Muhammad Sami Ur Rehman",
  "id": "ABF-6865-2020"
 },
 {
  "name": " Mah Rukh Rehman",
  "id": "HHI-7962-2022"
 },
 {
  "name": " Inam Ur Rehman",
  "id": "DWJ-3856-2022"
 },
 {
  "name": " Hafiz M. Abdur Rehman",
  "id": "GDI-4011-2022"
 },
 {
  "name": " Fazeelat Rehman",
  "id": "DMH-8712-2022"
 },
 {
  "name": " Faisal UL Rehman",
  "id": "AAI-4929-2021"
 },
 {
  "name": " Areeba Rehman",
  "id": "DNS-1369-2022"
 },
 {
  "name": " Muhammad Rehan",
  "id": "DMY-1097-2022"
 },
 {
  "name": " M. Rehan",
  "id": "INR-9399-2023"
 },
 {
  "name": " Asmad Bin Abdul Razzaque",
  "id": "HPO-8376-2023"
 },
 {
  "name": " Abdul Razzaque",
  "id": "FSM-5741-2022"
 },
 {
  "name": " Asghar A. Razzaqi",
  "id": "GBR-3269-2022"
 },
 {
  "name": " Muhammad Mustafa Raziq",
  "id": "AAE-8046-2019"
 },
 {
  "name": " Alia Razia",
  "id": "DNZ-6440-2022"
 },
 {
  "name": " Aden Razaq",
  "id": "DMM-5784-2022"
 },
 {
  "name": " Tanzeela Raza",
  "id": "FSP-2403-2022"
 },
 {
  "name": " Muhammad Arslan Raza",
  "id": "DUF-2973-2022"
 },
 {
  "name": " M. Hassan Raza",
  "id": "DTV-2908-2022"
 },
 {
  "name": " M. Raza",
  "id": "HNM-9765-2023"
 },
 {
  "name": " Faisal Raza",
  "id": "AAX-5143-2020"
 },
 {
  "name": " Arsalan Raza",
  "id": "GVS-5807-2022"
 },
 {
  "name": " Ali Raza",
  "id": "HQV-7442-2023"
 },
 {
  "name": " Abid Raza",
  "id": "ABA-4728-2021"
 },
 {
  "name": " Usman Rauf",
  "id": "DOQ-9361-2022"
 },
 {
  "name": " Momina Rauf",
  "id": "DPU-7590-2022"
 },
 {
  "name": " Bilal Rauf",
  "id": "DXN-3864-2022"
 },
 {
  "name": " A. Rauf",
  "id": "DVL-5985-2022"
 },
 {
  "name": " Tahir Abdul Hussain Ratlamwala",
  "id": "I-1132-2019"
 },
 {
  "name": " Mommana Ali Rathore",
  "id": "GGS-3400-2022"
 },
 {
  "name": " Shahzad Rasool",
  "id": "AAE-8858-2019"
 },
 {
  "name": " Samavia Rasool",
  "id": "DPO-8580-2022"
 },
 {
  "name": " Zubaida Rashid",
  "id": "DOI-2069-2022"
 },
 {
  "name": " Shagufta Rashid",
  "id": "FTL-4082-2022"
 },
 {
  "name": " Lubaba Rashid",
  "id": "GNE-1353-2022"
 },
 {
  "name": " Imran Rashid",
  "id": "FXL-0910-2022"
 },
 {
  "name": " Aqsa Rashid",
  "id": "T-5878-2018"
 },
 {
  "name": " Amir Rashid",
  "id": "IHJ-6196-2023"
 },
 {
  "name": " Amir Rashid",
  "id": "FVC-6880-2022"
 },
 {
  "name": " Adnan Rashid",
  "id": "ABA-8343-2021"
 },
 {
  "name": " Bushra Rasheed",
  "id": "GSB-7987-2022"
 },
 {
  "name": " Sadaf Rani",
  "id": "FRN-0227-2022"
 },
 {
  "name": " Tauseef Rana",
  "id": "CBU-6462-2022"
 },
 {
  "name": " Nosheen Rana",
  "id": "V-2118-2019"
 },
 {
  "name": " Aneeqa Ramzan",
  "id": "AAW-3791-2021"
 },
 {
  "name": " Muhammad Imran Rameel",
  "id": "FXO-9981-2022"
 },
 {
  "name": " Hira Raja",
  "id": "FUV-4276-2022"
 },
 {
  "name": " Hafsa Raja",
  "id": "FRI-4522-2022"
 },
 {
  "name": " Zainab A. Rahman",
  "id": "FTJ-8938-2022"
 },
 {
  "name": " Mamnoon Rahman",
  "id": "GPW-2500-2022"
 },
 {
  "name": " Anis U. Rahman",
  "id": "HZQ-4658-2023"
 },
 {
  "name": " Anees Ur Rahman",
  "id": "HVQ-9804-2023"
 },
 {
  "name": " Abdur Rahman",
  "id": "AAS-9132-2021"
 },
 {
  "name": " Abdur Rahman",
  "id": "HZA-5193-2023"
 },
 {
  "name": " Azizur Rahim",
  "id": "HLX-0725-2023"
 },
 {
  "name": " A. Rahim",
  "id": "DPH-7964-2022"
 },
 {
  "name": " Daneyal Rafique",
  "id": "FTQ-4385-2022"
 },
 {
  "name": " Mehak Rafiq",
  "id": "E-9986-2017"
 },
 {
  "name": " M. Rafiq",
  "id": "HGH-9810-2022"
 },
 {
  "name": " Muhammad U. Rafi",
  "id": "INY-0935-2023"
 },
 {
  "name": " Abdur Rafay",
  "id": "GCH-2629-2022"
 },
 {
  "name": " Muhammad Raees",
  "id": "HLF-6668-2023"
 },
 {
  "name": " Rabab Rabbani",
  "id": "GLZ-1970-2022"
 },
 {
  "name": " HINA RAJA",
  "id": "AAR-5423-2021"
 },
 {
  "name": " O RABI",
  "id": "FST-9919-2022"
 },
 {
  "name": " Zunaira Qureshi",
  "id": "GFP-9360-2022"
 },
 {
  "name": " Sidra Qureshi",
  "id": "GZH-1774-2022"
 },
 {
  "name": " Shafiq-Ur-Rehman Qureshi",
  "id": "DNU-4343-2022"
 },
 {
  "name": " MS Qureshi",
  "id": "GXE-6001-2022"
 },
 {
  "name": " Hassaan Khaliq Qureshi",
  "id": "FWI-5829-2022"
 },
 {
  "name": " Anum Qureshi",
  "id": "DMD-9143-2022"
 },
 {
  "name": " Fatima Quddos",
  "id": "GBT-5109-2022"
 },
 {
  "name": " Sharfah Ahmad Qazi",
  "id": "GNL-7311-2022"
 },
 {
  "name": " Zuhra Qayyum",
  "id": "GNV-9745-2022"
 },
 {
  "name": " T. Qayyum",
  "id": "FRN-0848-2022"
 },
 {
  "name": " Atif Qayyum",
  "id": "FZR-6527-2022"
 },
 {
  "name": " Ahmed Abdul Qayyum",
  "id": "AAV-2390-2021"
 },
 {
  "name": " Ahmed A. Qayyum",
  "id": "DOX-5551-2022"
 },
 {
  "name": " U. Qasim",
  "id": "DNQ-3620-2022"
 },
 {
  "name": " Muhammad Qamar-ul-Hassan",
  "id": "FUU-2438-2022"
 },
 {
  "name": " Usman Qamar",
  "id": "AAB-5656-2020"
 },
 {
  "name": " Sana Ullah Qamar",
  "id": "GXJ-8486-2022"
 },
 {
  "name": " Izza Qamar",
  "id": "HJQ-7547-2023"
 },
 {
  "name": " Ali Mustafa Qamar",
  "id": "A-1740-2012"
 },
 {
  "name": " Abdullah Qamar",
  "id": "FRK-0370-2022"
 },
 {
  "name": " Saad Qaisar",
  "id": "GBV-3552-2022"
 },
 {
  "name": " Mahmood Qaisar",
  "id": "GMZ-0549-2022"
 },
 {
  "name": " Sana Qadir",
  "id": "FUS-1098-2022"
 },
 {
  "name": " G. Prestopino",
  "id": "FZA-2355-2022"
 },
 {
  "name": " Riccardo Pezzilli",
  "id": "GBP-8375-2022"
 },
 {
  "name": " Nazia Perwiaz",
  "id": "DKN-7432-2022"
 },
 {
  "name": " Farrukh Pervez",
  "id": "GBQ-8621-2022"
 },
 {
  "name": " Saima Perveen",
  "id": "HWK-4299-2023"
 },
 {
  "name": " N. Pervaiz",
  "id": "FSH-6220-2022"
 },
 {
  "name": " Hina Pervaiz",
  "id": "FRL-1585-2022"
 },
 {
  "name": " Erum Pervaiz",
  "id": "DMJ-1036-2022"
 },
 {
  "name": " Mehwish Pasha",
  "id": "FQO-3610-2022"
 },
 {
  "name": " Arshi Parvaiz",
  "id": "HLI-5845-2023"
 },
 {
  "name": " Rehan Zafar Paracha",
  "id": "DWC-7571-2022"
 },
 {
  "name": " Muhammad Faheem Khalil Paracha",
  "id": "GND-7260-2022"
 },
 {
  "name": " Muhammad Ali Paracha",
  "id": "AAE-7072-2019"
 },
 {
  "name": " Ishwa Obaid",
  "id": "GMM-3940-2022"
 },
 {
  "name": " Asfia Obaid",
  "id": "FOO-3146-2022"
 },
 {
  "name": " Ammara Nusrat",
  "id": "FRQ-2485-2022"
 },
 {
  "name": " Muhammad Numan",
  "id": "DWM-5680-2022"
 },
 {
  "name": " Shabana Noureen",
  "id": "DWM-2873-2022"
 },
 {
  "name": " Fatima Noureen",
  "id": "GNS-1591-2022"
 },
 {
  "name": " Faryal Nosheen",
  "id": "DKN-0058-2022"
 },
 {
  "name": " Zarish Noreen",
  "id": "DKL-9136-2022"
 },
 {
  "name": " Tayyaba Noor",
  "id": "DJW-0863-2022"
 },
 {
  "name": " Saman Noor",
  "id": "DJW-7960-2022"
 },
 {
  "name": " Norina Noor",
  "id": "DLJ-4528-2022"
 },
 {
  "name": " Mudassar Noor",
  "id": "DIV-4135-2022"
 },
 {
  "name": " Muhammad Noman",
  "id": "HIO-9701-2022"
 },
 {
  "name": " Zahid Nisar",
  "id": "AAO-3381-2021"
 },
 {
  "name": " Shibli Nisar",
  "id": "DJZ-6982-2022"
 },
 {
  "name": " Salman Nisar",
  "id": "DKE-6882-2022"
 },
 {
  "name": " Maryum Nisar",
  "id": "AAZ-8470-2021"
 },
 {
  "name": " Hamza Nisar",
  "id": "FOO-6499-2022"
 },
 {
  "name": " Asia Nisar",
  "id": "HHR-8599-2022"
 },
 {
  "name": " Muhammad Bilal Khan Niazi",
  "id": "GBG-4964-2022"
 },
 {
  "name": " Muaz Niazi",
  "id": "B-7567-2009"
 },
 {
  "name": " Maha Niazi",
  "id": "FPU-7545-2022"
 },
 {
  "name": " M. B. Niazi",
  "id": "DIA-4611-2022"
 },
 {
  "name": " Ihtisham Ul Haq Khan Niazi",
  "id": "HIG-0545-2022"
 },
 {
  "name": " Muneeb Niaz",
  "id": "GPA-8316-2022"
 },
 {
  "name": " Ayesha Nazuk",
  "id": "FRV-1540-2022"
 },
 {
  "name": " Saqib Nazir",
  "id": "DKY-8194-2022"
 },
 {
  "name": " Sadia Nazir",
  "id": "DTG-2112-2022"
 },
 {
  "name": " N. Nazir",
  "id": "FQA-2234-2022"
 },
 {
  "name": " Farzana Nazir",
  "id": "AFM-9747-2022"
 },
 {
  "name": " Neelma Naz",
  "id": "FNN-6833-2022"
 },
 {
  "name": " Kanwal Naz",
  "id": "DLD-8179-2022"
 },
 {
  "name": " Iram Naz",
  "id": "GVS-2533-2022"
 },
 {
  "name": " Sanam Nayab",
  "id": "GZI-8547-2022"
 },
 {
  "name": " Muhammad N. N. Nawaz",
  "id": "HIX-6903-2022"
 },
 {
  "name": " Muhammad Nawaz",
  "id": "FOS-7596-2022"
 },
 {
  "name": " Fahad Nawaz",
  "id": "GQX-4582-2022"
 },
 {
  "name": " Arooj Nawaz",
  "id": "FNU-6732-2022"
 },
 {
  "name": " Afrah Nawaz",
  "id": "FQN-3129-2022"
 },
 {
  "name": " Samina Naveed",
  "id": "DKS-9702-2022"
 },
 {
  "name": " Muhammad Haris Naveed",
  "id": "HQI-2380-2023"
 },
 {
  "name": " Kanwal Naveed",
  "id": "FPN-0478-2022"
 },
 {
  "name": " Abdul Basit Naveed",
  "id": "FOZ-7447-2022"
 },
 {
  "name": " Amnah Nasrullah",
  "id": "GXR-4847-2022"
 },
 {
  "name": " Samavi Nasir",
  "id": "DJR-9012-2022"
 },
 {
  "name": " Sadia Nasir",
  "id": "HHC-0761-2022"
 },
 {
  "name": " Muhammad Nasir",
  "id": "HDO-4255-2022"
 },
 {
  "name": " Khuzaeymah Nasir",
  "id": "GWH-2322-2022"
 },
 {
  "name": " Jehanzeb Nasir",
  "id": "GPV-2024-2022"
 },
 {
  "name": " Hasan Arshad Nasir",
  "id": "GYI-7894-2022"
 },
 {
  "name": " Habib Nasir",
  "id": "AAA-3327-2019"
 },
 {
  "name": " Esha Sadia Nasir",
  "id": "HLL-5715-2023"
 },
 {
  "name": " Dr.-Ing. Abdur Rehman Nasir",
  "id": "HJZ-3157-2023"
 },
 {
  "name": " R. Naseer",
  "id": "FOZ-7516-2022"
 },
 {
  "name": " R. Naseer",
  "id": "GCA-4718-2022"
 },
 {
  "name": " Muhammad Nihal Naseer",
  "id": "AAG-1643-2021"
 },
 {
  "name": " Faiza Naseer",
  "id": "DJH-4413-2022"
 },
 {
  "name": " Afshan Naseem",
  "id": "ACA-2120-2022"
 },
 {
  "name": " Salman Raza Naqvi",
  "id": "AFW-4797-2022"
 },
 {
  "name": " Salman Naqvi",
  "id": "L-1005-2019"
 },
 {
  "name": " Bakare Najimdeen",
  "id": "HDM-8780-2022"
 },
 {
  "name": " Antash Najib",
  "id": "DKN-9415-2022"
 },
 {
  "name": " Fawad Ahmed Najam",
  "id": "CCA-6096-2022"
 },
 {
  "name": " Zohaib Sattar Nagra",
  "id": "HLA-8520-2023"
 },
 {
  "name": " Nida Naeem",
  "id": "DYA-5923-2022"
 },
 {
  "name": " M. B. Naeem",
  "id": "DGX-7145-2022"
 },
 {
  "name": " Afnan Naeem",
  "id": "FNY-2246-2022"
 },
 {
  "name": " Sohail Nadeem",
  "id": "I-5248-2013"
 },
 {
  "name": " Muhamad Umar Nadeem",
  "id": "DHH-8211-2022"
 },
 {
  "name": " Momina Nadeem",
  "id": "HDV-5596-2022"
 },
 {
  "name": " Aroosa Younis Nadeem",
  "id": "GMA-3321-2022"
 },
 {
  "name": " Amina Nadeem",
  "id": "DHT-1360-2022"
 },
 {
  "name": " Deedar Nabi",
  "id": "GBA-8262-2022"
 },
 {
  "name": " NAUMAN",
  "id": "FSI-8102-2022"
 },
 {
  "name": " Sidra Muzaffar",
  "id": "GXD-1659-2022"
 },
 {
  "name": " Farrukh Mustahsan",
  "id": "DVC-8077-2022"
 },
 {
  "name": " Meraj Mustafa",
  "id": "IGH-0445-2023"
 },
 {
  "name": " Meraj Mustafa Hashmi",
  "id": "P-1769-2014"
 },
 {
  "name": " Hafiz Syed Muhammad Muslim",
  "id": "GNP-1603-2022"
 },
 {
  "name": " Shehla Mushtaq",
  "id": "HGV-1934-2022"
 },
 {
  "name": " Sardar Farhan Mushtaq",
  "id": "GWI-0143-2022"
 },
 {
  "name": " Saima Mushtaq",
  "id": "FZH-7993-2022"
 },
 {
  "name": " Moniba Mushtaq",
  "id": "DJJ-8900-2022"
 },
 {
  "name": " Malaika Mushtaq",
  "id": "DIZ-1084-2022"
 },
 {
  "name": " Ammar Mushtaq",
  "id": "DII-5718-2022"
 },
 {
  "name": " Shahid Ali Murtza",
  "id": "FOQ-2600-2022"
 },
 {
  "name": " Zahid Murtaza",
  "id": "DKZ-5755-2022"
 },
 {
  "name": " Malik Hamza Murtaza",
  "id": "AAR-4574-2020"
 },
 {
  "name": " Ghulam Murtaza",
  "id": "FZE-8660-2022"
 },
 {
  "name": " Didar Murad",
  "id": "FNZ-3217-2022"
 },
 {
  "name": " Tehmina Munir",
  "id": "DHT-6574-2022"
 },
 {
  "name": " S. Munir",
  "id": "GYX-4722-2022"
 },
 {
  "name": " R Munir",
  "id": "GQW-2627-2022"
 },
 {
  "name": " Muhammad Asim Munir",
  "id": "HNH-3101-2023"
 },
 {
  "name": " Faiza Munir",
  "id": "DKA-6661-2022"
 },
 {
  "name": " Dr Madiha Munir",
  "id": "HNB-8257-2023"
 },
 {
  "name": " Adnan Munir",
  "id": "AAR-5756-2021"
 },
 {
  "name": " Imran Qayyum Mundial",
  "id": "GMF-7693-2022"
 },
 {
  "name": " Huda Munawar",
  "id": "HNZ-5372-2023"
 },
 {
  "name": " Hammad Munawar",
  "id": "GQV-8774-2022"
 },
 {
  "name": " Ahmed Umar Munawar",
  "id": "FNS-1526-2022"
 },
 {
  "name": " Wajid Mumtaz",
  "id": "GCC-9533-2022"
 },
 {
  "name": " Rafia Mumtaz",
  "id": "O-7715-2016"
 },
 {
  "name": " Muhammad Zeeshan Mumtaz",
  "id": "FPY-1708-2022"
 },
 {
  "name": " M. N. Mumtaz",
  "id": "DHA-0922-2022"
 },
 {
  "name": " Faisal Mumtaz",
  "id": "GYI-9778-2022"
 },
 {
  "name": " Asad Mumtaz",
  "id": "DXW-1018-2022"
 },
 {
  "name": " Mamuna Mukhtar",
  "id": "HHE-1501-2022"
 },
 {
  "name": " Amir Mukhtar",
  "id": "DGX-6712-2022"
 },
 {
  "name": " Usman Muhammad",
  "id": "HTL-4089-2023"
 },
 {
  "name": " SOHAIL Muhammad",
  "id": "S-1603-2017"
 },
 {
  "name": " Rabiah Muhammad",
  "id": "HNI-7953-2023"
 },
 {
  "name": " Sharif Muhammad Nauman",
  "id": "FPE-5699-2022"
 },
 {
  "name": " Nabeeha Ehsan Mughal",
  "id": "GSG-8847-2022"
 },
 {
  "name": " Laiba Mudusar",
  "id": "FQY-4076-2022"
 },
 {
  "name": " Uzair Mudassir",
  "id": "HNM-3507-2023"
 },
 {
  "name": " Aamir Mubashir",
  "id": "HTJ-8239-2023"
 },
 {
  "name": " Aamir Mubashar",
  "id": "DZA-5952-2022"
 },
 {
  "name": " Aamir Mubashar",
  "id": "G-3743-2013"
 },
 {
  "name": " Maryam Mubarak",
  "id": "DGW-3243-2022"
 },
 {
  "name": " Muhammad Zubair Ali Moughal",
  "id": "GBG-7789-2022"
 },
 {
  "name": " Syed Kumayl Raza Moosavi",
  "id": "DHJ-9031-2022"
 },
 {
  "name": " Muhammad Yasin Mohsin",
  "id": "HUQ-1116-2023"
 },
 {
  "name": " Mashood Mohammad Mohsan",
  "id": "GRC-6415-2022"
 },
 {
  "name": " Mohammad A. Mohammad",
  "id": "FMQ-1389-2022"
 },
 {
  "name": " Syed I. Moazzam",
  "id": "GDQ-0729-2022"
 },
 {
  "name": " Muhammad Moazzam",
  "id": "HZK-0017-2023"
 },
 {
  "name": " Muhammad Zeeshan Mirza",
  "id": "J-6232-2019"
 },
 {
  "name": " Muhammad Omer Mirza",
  "id": "DHN-9746-2022"
 },
 {
  "name": " M. Mirza",
  "id": "GNT-2084-2022"
 },
 {
  "name": " Fatima Javed Mirza",
  "id": "FME-0522-2022"
 },
 {
  "name": " Waheed Miran",
  "id": "DUV-1299-2022"
 },
 {
  "name": " Mariam Mir",
  "id": "ABA-3918-2021"
 },
 {
  "name": " Aneeque Ahmed Mir",
  "id": "DTK-6387-2022"
 },
 {
  "name": " Rehman U. Mian",
  "id": "DWA-1604-2022"
 },
 {
  "name": " Rashida Ali Memon",
  "id": "DWS-2666-2022"
 },
 {
  "name": " Mumtaz Ali Memon",
  "id": "Q-1479-2016"
 },
 {
  "name": " Attaullah Y. Memon",
  "id": "DXB-8070-2022"
 },
 {
  "name": " Naila Mehreen",
  "id": "GCO-5054-2022"
 },
 {
  "name": " Tajwar Mehmood",
  "id": "HOU-3223-2023"
 },
 {
  "name": " Tahir Mehmood",
  "id": "AAE-7083-2019"
 },
 {
  "name": " M. Adil Mehmood",
  "id": "FKC-5011-2022"
 },
 {
  "name": " Kashif Mehmood",
  "id": "HYC-8560-2023"
 },
 {
  "name": " Rimsha Mehek",
  "id": "FJQ-5307-2022"
 },
 {
  "name": " Wajeeha Mehdi",
  "id": "HFF-1402-2022"
 },
 {
  "name": " Rifat Mehdi",
  "id": "FKE-4922-2022"
 },
 {
  "name": " Hafiz Muhammad Mehdi",
  "id": "DFP-2525-2022"
 },
 {
  "name": " Ayesha Mehboob",
  "id": "FLS-2295-2022"
 },
 {
  "name": " Naveed Mazhar",
  "id": "ABI-6644-2020"
 },
 {
  "name": " Muhammad Mazhar",
  "id": "GDQ-9845-2022"
 },
 {
  "name": " Farrukh Mazhar",
  "id": "DWK-5457-2022"
 },
 {
  "name": " Abdur Rehman Mazhar",
  "id": "DVS-6261-2022"
 },
 {
  "name": " Awais Mazahir",
  "id": "GXB-7661-2022"
 },
 {
  "name": " Muhammad Matloob",
  "id": "FKZ-7802-2022"
 },
 {
  "name": " Usama Masood",
  "id": "FKI-9256-2022"
 },
 {
  "name": " Sabeen Masood",
  "id": "DFP-7152-2022"
 },
 {
  "name": " Mehar Masood",
  "id": "HZL-1465-2023"
 },
 {
  "name": " Madahiah Bint E. Masood",
  "id": "IML-3451-2023"
 },
 {
  "name": " Asif Masood",
  "id": "DER-2168-2022"
 },
 {
  "name": " Syed Fawad Mashhadi",
  "id": "FKI-1276-2022"
 },
 {
  "name": " Tuba Maryam",
  "id": "DEU-6184-2022"
 },
 {
  "name": " Shahid Maryam",
  "id": "FKH-8067-2022"
 },
 {
  "name": " Rida Maryam",
  "id": "FKZ-0101-2022"
 },
 {
  "name": " Maryam Maryam",
  "id": "GMS-6045-2022"
 },
 {
  "name": " Laiba Maryam",
  "id": "HLL-2631-2023"
 },
 {
  "name": " Fareeha Marriam",
  "id": "HKI-8382-2023"
 },
 {
  "name": " Maria",
  "id": "ABG-7201-2021"
 },
 {
  "name": " Zain Maqsood",
  "id": "DXG-2798-2022"
 },
 {
  "name": " Z. Maqsood",
  "id": "FKR-8199-2022"
 },
 {
  "name": " Ifrah Maqsood",
  "id": "HOJ-8070-2023"
 },
 {
  "name": " Nida Maqbool",
  "id": "FJF-0660-2022"
 },
 {
  "name": " Ayesha Maqbool",
  "id": "HCI-5538-2022"
 },
 {
  "name": " A. Maqbool",
  "id": "GMR-9612-2022"
 },
 {
  "name": " Sobia Manzoor",
  "id": "FKF-4418-2022"
 },
 {
  "name": " Kamran Manzoor",
  "id": "HUV-3110-2023"
 },
 {
  "name": " Sumaiya Mansoor",
  "id": "FPB-0979-2022"
 },
 {
  "name": " Muhammad Adil Mansoor",
  "id": "ABG-7072-2021"
 },
 {
  "name": " Mohtashim Mansoor",
  "id": "Q-6347-2017"
 },
 {
  "name": " Asif Mansoor",
  "id": "FLC-0646-2022"
 },
 {
  "name": " Rahman Mamnoon",
  "id": "GXQ-7771-2022"
 },
 {
  "name": " Zahida Malik",
  "id": "FJA-4640-2022"
 },
 {
  "name": " Waqar A. Malik",
  "id": "DGE-2493-2022"
 },
 {
  "name": " Umer Malik",
  "id": "GWH-3210-2022"
 },
 {
  "name": " Sheza Malik",
  "id": "FLH-0798-2022"
 },
 {
  "name": " Sarmad Majeed Malik",
  "id": "DFD-6349-2022"
 },
 {
  "name": " Nishat Malik",
  "id": "GQR-4595-2022"
 },
 {
  "name": " Naveed Ahmad Malik",
  "id": "HKX-9201-2023"
 },
 {
  "name": " Muhammad Mahad Malik",
  "id": "DEG-4980-2022"
 },
 {
  "name": " Muhammad Malik",
  "id": "AFK-4955-2022"
 },
 {
  "name": " Mohammad Bilal Malik",
  "id": "FYF-0232-2022"
 },
 {
  "name": " Mehreen Malik",
  "id": "GXN-0584-2022"
 },
 {
  "name": " Maida Malik",
  "id": "GRB-6517-2022"
 },
 {
  "name": " Jahanzaib Malik",
  "id": "GDF-9820-2022"
 },
 {
  "name": " J. Malik",
  "id": "GQA-0651-2022"
 },
 {
  "name": " Fouzia Perveen Malik",
  "id": "FLJ-0596-2022"
 },
 {
  "name": " Fahad Mumtaz Malik",
  "id": "HWH-5579-2023"
 },
 {
  "name": " Ali Malik",
  "id": "HTG-1309-2023"
 },
 {
  "name": " Afia Malik",
  "id": "FLO-7831-2022"
 },
 {
  "name": " Abdul Malik",
  "id": "GZF-3889-2022"
 },
 {
  "name": " Muhammad Makki",
  "id": "FLD-8959-2022"
 },
 {
  "name": " Iqra Majoka",
  "id": "HNW-5595-2023"
 },
 {
  "name": " Mahnoor Majid",
  "id": "FHI-8885-2022"
 },
 {
  "name": " Bushra Majeed",
  "id": "DXH-1986-2022"
 },
 {
  "name": " Ayesha Isani Majeed",
  "id": "FHX-2966-2022"
 },
 {
  "name": " Minhas Mahsud",
  "id": "DFH-9992-2022"
 },
 {
  "name": " Mariam Mahmood",
  "id": "HFT-3990-2022"
 },
 {
  "name": " Karishma Mahmood",
  "id": "DDJ-6474-2022"
 },
 {
  "name": " Fatimah Mahmood",
  "id": "DDO-1334-2022"
 },
 {
  "name": " Azhar Mahmood",
  "id": "DUJ-8783-2022"
 },
 {
  "name": " Ahrar Mahmood",
  "id": "FKF-8179-2022"
 },
 {
  "name": " MOHAMMAD MUJAHID",
  "id": "AAG-3779-2020"
 },
 {
  "name": " ASIFA MAJEED",
  "id": "N-3767-2017"
 },
 {
  "name": " Faiza Lughmani",
  "id": "FJN-7366-2022"
 },
 {
  "name": " Adil Loya",
  "id": "HGH-1529-2022"
 },
 {
  "name": " Adil Loya",
  "id": "GQO-9725-2022"
 },
 {
  "name": " Rida Hameed Lodhi",
  "id": "FMI-8277-2022"
 },
 {
  "name": " Aqsa Saqib Lodhi",
  "id": "GNK-6609-2022"
 },
 {
  "name": " Rabia Liaquat",
  "id": "GDX-8384-2022"
 },
 {
  "name": " Muwahida Liaquat",
  "id": "AAS-1298-2020"
 },
 {
  "name": " Usman Liaqat",
  "id": "AAE-3960-2021"
 },
 {
  "name": " Talha Liaqat",
  "id": "FKS-8971-2022"
 },
 {
  "name": " Asia Liaqat",
  "id": "DCH-6328-2022"
 },
 {
  "name": " A. Liaqat",
  "id": "DEI-3172-2022"
 },
 {
  "name": " Claudio Leonardi",
  "id": "DBA-8750-2022"
 },
 {
  "name": " Seemab Latif",
  "id": "FYM-3048-2022"
 },
 {
  "name": " Bushra Latif",
  "id": "FGN-7180-2022"
 },
 {
  "name": " Tahira Anwar Lashari",
  "id": "AAB-6790-2020"
 },
 {
  "name": " Ume Laila",
  "id": "FJK-2115-2022"
 },
 {
  "name": " Faraz Kunwar",
  "id": "FDQ-4673-2022"
 },
 {
  "name": " Sagar Kumar",
  "id": "FHQ-8092-2022"
 },
 {
  "name": " Salma Kulsoom",
  "id": "GME-0415-2022"
 },
 {
  "name": " Kousain Kousar",
  "id": "GRJ-3707-2022"
 },
 {
  "name": " Humaira Kousar",
  "id": "FCS-8627-2022"
 },
 {
  "name": " Komal",
  "id": "AGJ-2518-2022"
 },
 {
  "name": " Q. Kiran",
  "id": "GCB-3580-2022"
 },
 {
  "name": " Yusra Sajid Kiani",
  "id": "FDD-6535-2022"
 },
 {
  "name": " Usama Bin Naseem Kiani",
  "id": "HDU-7056-2022"
 },
 {
  "name": " Sana Khyzer",
  "id": "FDK-2394-2022"
 },
 {
  "name": " Khawar Khurshid",
  "id": "FCE-1203-2022"
 },
 {
  "name": " Hamza Khurshid",
  "id": "CXO-2216-2022"
 },
 {
  "name": " Rafiq Khosa",
  "id": "FEV-7248-2022"
 },
 {
  "name": " Malik Abid Hussain Khokhar",
  "id": "GQU-7555-2022"
 },
 {
  "name": " M.Fahim Khokhar",
  "id": "ABB-6157-2021"
 },
 {
  "name": " Fakhar Uddin Khilji",
  "id": "HNL-5670-2023"
 },
 {
  "name": " Umer Khayyam",
  "id": "FFC-3875-2022"
 },
 {
  "name": " Muhammad Irfan Khawar",
  "id": "FHC-9998-2022"
 },
 {
  "name": " Sajid Gul Khawaja",
  "id": "GBO-2664-2022"
 },
 {
  "name": " Fahad Iqbal Khawaja",
  "id": "ABE-6468-2021"
 },
 {
  "name": " Hasan Ali Khattak",
  "id": "N-4656-2014"
 },
 {
  "name": " Beenish Khan Khattak",
  "id": "GQU-1982-2022"
 },
 {
  "name": " Alishba Khattak",
  "id": "FDU-6589-2022"
 },
 {
  "name": " Abraiz Khattak",
  "id": "C-3911-2016"
 },
 {
  "name": " Farooq Azam Khanzada",
  "id": "FBV-0584-2022"
 },
 {
  "name": " Saeeda Khanum",
  "id": "AAE-1006-2021"
 },
 {
  "name": " Zuhair S Khan",
  "id": "F-7929-2011"
 },
 {
  "name": " Zikriya Khan",
  "id": "GOV-7020-2022"
 },
 {
  "name": " Ziaullh Khan",
  "id": "GSG-0028-2022"
 },
 {
  "name": " Ziaullah Khan",
  "id": "CXI-4999-2022"
 },
 {
  "name": " Zia A. Khan",
  "id": "HQI-1177-2023"
 },
 {
  "name": " Zeashan H Khan",
  "id": "A-2059-2012"
 },
 {
  "name": " Zain Ullah Khan",
  "id": "FEQ-1029-2022"
 },
 {
  "name": " Zahoor Khan",
  "id": "R-5965-2019"
 },
 {
  "name": " Z. S. Khan",
  "id": "CXG-3083-2022"
 },
 {
  "name": " Waqar Khan",
  "id": "FYM-2487-2022"
 },
 {
  "name": " Usman Ahmed Khan",
  "id": "ILB-4320-2023"
 },
 {
  "name": " Usman Khan",
  "id": "HGK-0161-2022"
 },
 {
  "name": " Uneeb Masood Khan",
  "id": "DVA-0564-2022"
 },
 {
  "name": " Tooba Javaid Khan",
  "id": "HXH-4498-2023"
 },
 {
  "name": " Tariq M. Khan",
  "id": "FEX-4546-2022"
 },
 {
  "name": " Tariq A. Khan",
  "id": "FDR-7272-2022"
 },
 {
  "name": " Sultani Mulk Khan",
  "id": "GLX-4164-2022"
 },
 {
  "name": " Shoaib Raza Khan",
  "id": "ABE-1912-2021"
 },
 {
  "name": " Shoab Ahmed Khan",
  "id": "FFH-2412-2022"
 },
 {
  "name": " Sher Jamal Khan",
  "id": "AAD-8549-2021"
 },
 {
  "name": " Sher Khan",
  "id": "DTO-7139-2022"
 },
 {
  "name": " Sheher Yar Khan",
  "id": "IDZ-5718-2023"
 },
 {
  "name": " Sharifullah Khan",
  "id": "FCL-7687-2022"
 },
 {
  "name": " Shamraiza Khan",
  "id": "FBO-8744-2022"
 },
 {
  "name": " Shahzad Khan",
  "id": "FYJ-1177-2022"
 },
 {
  "name": " Shahid Nawaz Khan",
  "id": "AAZ-5141-2020"
 },
 {
  "name": " Shahid Nawaz Khan",
  "id": "GLU-2654-2022"
 },
 {
  "name": " Shahid Ali Khan",
  "id": "AAL-6431-2021"
 },
 {
  "name": " Sana Gohar Khan",
  "id": "IDN-8931-2023"
 },
 {
  "name": " Salman Khan",
  "id": "HNE-7411-2023"
 },
 {
  "name": " Saleem Ahmed Khan",
  "id": "FHK-1448-2022"
 },
 {
  "name": " Sabih Ahmad Khan",
  "id": "GMA-2607-2022"
 },
 {
  "name": " Rukaiza Khan",
  "id": "FEP-3070-2022"
 },
 {
  "name": " Rijah Khan",
  "id": "HHR-0437-2022"
 },
 {
  "name": " Ramsha Khan",
  "id": "HWE-8127-2023"
 },
 {
  "name": " Ramsha Khan",
  "id": "FYF-2488-2022"
 },
 {
  "name": " Rameez Khan",
  "id": "HME-0763-2023"
 },
 {
  "name": " R. A. Khan",
  "id": "CYG-5422-2022"
 },
 {
  "name": " Qasim Umar Khan",
  "id": "HLR-4919-2023"
 },
 {
  "name": " Obaid Khan",
  "id": "CYG-9397-2022"
 },
 {
  "name": " Niaz Bahadur Khan",
  "id": "ACU-7263-2022"
 },
 {
  "name": " Niaz B Khan",
  "id": "C-5539-2016"
 },
 {
  "name": " Naseer M Khan",
  "id": "ADG-0554-2022"
 },
 {
  "name": " Naila Khan",
  "id": "FDU-1403-2022"
 },
 {
  "name": " Naila Khan",
  "id": "CYP-7497-2022"
 },
 {
  "name": " Muzammil Ahmed Khan",
  "id": "HLY-0133-2023"
 },
 {
  "name": " Muzammil Khan",
  "id": "GOU-7036-2022"
 },
 {
  "name": " Musharib Khan",
  "id": "FGY-2030-2022"
 },
 {
  "name": " Musharib Khan",
  "id": "H-2441-2015"
 },
 {
  "name": " Musaad Zaheer Nazir Khan",
  "id": "DWD-0979-2022"
 },
 {
  "name": " Muhammad Zeeshan Ali Ali Khan",
  "id": "HTP-3861-2023"
 },
 {
  "name": " Muhammad Zeeshan Ali Khan",
  "id": "DUA-8111-2022"
 },
 {
  "name": " Muhammad Zarrar Khan",
  "id": "DTF-2519-2022"
 },
 {
  "name": " Muhammad Zamir Khan",
  "id": "HVE-1223-2023"
 },
 {
  "name": " Muhammad Wasif Khan",
  "id": "HFQ-8200-2022"
 },
 {
  "name": " Muhammad Umar Khan",
  "id": "AAH-1646-2020"
 },
 {
  "name": " Muhammad U. Khan",
  "id": "FVS-7409-2022"
 },
 {
  "name": " Muhammad Salman Khan",
  "id": "HTF-8004-2023"
 },
 {
  "name": " Muhammad Nouman Aslam Khan",
  "id": "AAL-2924-2021"
 },
 {
  "name": " Muhammad Marghoob Khan",
  "id": "IDZ-5063-2023"
 },
 {
  "name": " Muhammad Jawad Khan",
  "id": "GQQ-1646-2022"
 },
 {
  "name": " Muhammad Imran Khan",
  "id": "GAX-0261-2022"
 },
 {
  "name": " Muhammad Ammad Khan",
  "id": "DVO-6462-2022"
 },
 {
  "name": " Mehreen Khan",
  "id": "FEX-1906-2022"
 },
 {
  "name": " Maryam Khan",
  "id": "DVW-8353-2022"
 },
 {
  "name": " Maryam Khan",
  "id": "FBH-7525-2022"
 },
 {
  "name": " Maryam Khan",
  "id": "FCN-0173-2022"
 },
 {
  "name": " Marrium Khan",
  "id": "GNR-4322-2022"
 },
 {
  "name": " Malik Muhammad Saud Sajid Khan",
  "id": "FXT-8993-2022"
 },
 {
  "name": " Majid Khan",
  "id": "G-1606-2018"
 },
 {
  "name": " Maham Khan",
  "id": "GVW-4368-2022"
 },
 {
  "name": " M. Adil Khan",
  "id": "GMG-8488-2022"
 },
 {
  "name": " Khushbukhat Khan",
  "id": "DTF-1346-2022"
 },
 {
  "name": " Khushbukhat Khan",
  "id": "ABD-1873-2020"
 },
 {
  "name": " Khurram Iqbal Ahmad Khan",
  "id": "HMQ-4966-2023"
 },
 {
  "name": " Karam Khan",
  "id": "FCH-9943-2022"
 },
 {
  "name": " Junaid Aziz Khan",
  "id": "AAQ-4578-2020"
 },
 {
  "name": " Jamal Khan",
  "id": "FGG-8681-2022"
 },
 {
  "name": " J. A. Khan",
  "id": "GVF-0737-2022"
 },
 {
  "name": " Irum Shahid Khan",
  "id": "HLX-5176-2023"
 },
 {
  "name": " Hassan Aqeel Khan",
  "id": "HJR-1644-2023"
 },
 {
  "name": " Haris Khan",
  "id": "ABF-1957-2021"
 },
 {
  "name": " Hammad Anis Khan",
  "id": "GQZ-2271-2022"
 },
 {
  "name": " Hamid Sharif Khan",
  "id": "AAQ-5573-2020"
 },
 {
  "name": " Hamdullah Khan",
  "id": "FCI-8849-2022"
 },
 {
  "name": " Hafiza Aroosa Aslam Khan",
  "id": "CYN-4628-2022"
 },
 {
  "name": " HA Khan",
  "id": "GMK-2448-2022"
 },
 {
  "name": " Firdos Khan",
  "id": "AAE-7252-2019"
 },
 {
  "name": " Fazal Maula Khan",
  "id": "FZU-5638-2022"
 },
 {
  "name": " Fawad Khan",
  "id": "N-4715-2017"
 },
 {
  "name": " Faryal Khan",
  "id": "CXQ-2475-2022"
 },
 {
  "name": " Farhan Hassan Khan",
  "id": "N-7235-2019"
 },
 {
  "name": " Fahd A. Khan",
  "id": "DVR-1926-2022"
 },
 {
  "name": " Dr Noor Ullah Khan",
  "id": "T-1567-2019"
 },
 {
  "name": " Daniyal Sajid Khan",
  "id": "HKQ-6333-2023"
 },
 {
  "name": " Azam Khan",
  "id": "HFD-3812-2022"
 },
 {
  "name": " Asad-Ur-Rehman Khan",
  "id": "DSF-3391-2022"
 },
 {
  "name": " Arslan Khan",
  "id": "HTN-3295-2023"
 },
 {
  "name": " Arshad Khan",
  "id": "FXY-2381-2022"
 },
 {
  "name": " Amna Khan",
  "id": "CZR-0495-2022"
 },
 {
  "name": " Ahmad Nawaz Khan",
  "id": "DVY-3211-2022"
 },
 {
  "name": " Adnan Ahmed Khan",
  "id": "HHR-0443-2022"
 },
 {
  "name": " Adam Khan",
  "id": "GXI-6617-2022"
 },
 {
  "name": " Abdul Salam Khan",
  "id": "AAL-5690-2021"
 },
 {
  "name": " Abdul Salam Khan",
  "id": "DRZ-2859-2022"
 },
 {
  "name": " Abd Ullah Khan",
  "id": "ABB-5040-2020"
 },
 {
  "name": " Aamir Khan",
  "id": "CXX-0011-2022"
 },
 {
  "name": " A. A. Khan",
  "id": "HZZ-1663-2023"
 },
 {
  "name": " Muhammad Waseem Khaliq",
  "id": "FHG-2710-2022"
 },
 {
  "name": " Ikram Khaliq",
  "id": "CYM-3609-2022"
 },
 {
  "name": " Mohsin Khalil",
  "id": "HRF-5316-2023"
 },
 {
  "name": " Khurram Khalil",
  "id": "GBB-2866-2022"
 },
 {
  "name": " Ihsan Ullah Khalil",
  "id": "AAX-8629-2020"
 },
 {
  "name": " Z. Khalid",
  "id": "HRT-0009-2023"
 },
 {
  "name": " Usama Khalid",
  "id": "AAE-6716-2022"
 },
 {
  "name": " Syeda Javariya Khalid",
  "id": "CYT-2962-2022"
 },
 {
  "name": " Shoaib Khalid",
  "id": "AGA-9912-2022"
 },
 {
  "name": " Muhammad Tanzeel Khalid",
  "id": "HFQ-3892-2022"
 },
 {
  "name": " Muhammad Hamza Khalid",
  "id": "ABH-1902-2021"
 },
 {
  "name": " Minahil Khalid",
  "id": "CZH-6748-2022"
 },
 {
  "name": " M. Khalid",
  "id": "FDR-7643-2022"
 },
 {
  "name": " Kashaf Khalid",
  "id": "FBP-9147-2022"
 },
 {
  "name": " Dr Farah Khalid",
  "id": "HTM-4724-2023"
 },
 {
  "name": " Sana Khadim",
  "id": "GOQ-7170-2022"
 },
 {
  "name": " Rehana Khadim",
  "id": "FCQ-6585-2022"
 },
 {
  "name": " Syed Saqib Ali Kazmi",
  "id": "FBP-3513-2022"
 },
 {
  "name": " Syed Naqash Haider Kazmi",
  "id": "CYU-0638-2022"
 },
 {
  "name": " Syed Ali Abbas Kazmi",
  "id": "DVW-6635-2022"
 },
 {
  "name": " Maemoona Kayani",
  "id": "GXA-0331-2022"
 },
 {
  "name": " Umara Kausar",
  "id": "FDV-2815-2022"
 },
 {
  "name": " M. Kataria",
  "id": "HFF-4301-2022"
 },
 {
  "name": " Amer Sohail Kashif",
  "id": "CYB-3974-2022"
 },
 {
  "name": " Abdul Kashif Janjua",
  "id": "HHP-1901-2022"
 },
 {
  "name": " Syed Shujaat Karim",
  "id": "CAF-7407-2022"
 },
 {
  "name": " Shahid Karim",
  "id": "DTN-7927-2022"
 },
 {
  "name": " Adnan Karim",
  "id": "GXN-6995-2022"
 },
 {
  "name": " Saira Kanwal",
  "id": "CXW-2268-2022"
 },
 {
  "name": " Maria Kanwal",
  "id": "HDT-2096-2022"
 },
 {
  "name": " Maria Kanwal",
  "id": "GZM-0550-2022"
 },
 {
  "name": " Muhammad Kamran",
  "id": "Z-1634-2018"
 },
 {
  "name": " Khashayar Kamran",
  "id": "CYA-9083-2022"
 },
 {
  "name": " Haseeb Kamran",
  "id": "CYC-3135-2022"
 },
 {
  "name": " Awais Mehmood Kamboh",
  "id": "DXE-8671-2022"
 },
 {
  "name": " Muhammad Daud Kamal",
  "id": "DUM-2907-2022"
 },
 {
  "name": " Khurram Kamal",
  "id": "FFY-7219-2022"
 },
 {
  "name": " Imtiaz Hussain Kalwar",
  "id": "HJQ-2927-2023"
 },
 {
  "name": " Nadia Kalsoom",
  "id": "GWR-8551-2022"
 },
 {
  "name": " Karam Dad Kallu",
  "id": "CXA-6037-2022"
 },
 {
  "name": " Muhammad Noor Kakar",
  "id": "AGQ-1421-2022"
 },
 {
  "name": " Kainat",
  "id": "CYY-6697-2022"
 },
 {
  "name": " Muhammad Owais Kaifi",
  "id": "CXO-8027-2022"
 },
 {
  "name": " HARIS AHMED KHAN",
  "id": "AEF-3311-2022"
 },
 {
  "name": " M KHALIL",
  "id": "FDS-1849-2022"
 },
 {
  "name": " A. Junaid",
  "id": "GXJ-7801-2022"
 },
 {
  "name": " Zahid Jumah",
  "id": "GOZ-9020-2022"
 },
 {
  "name": " Alishba Jehangir",
  "id": "CXB-0720-2022"
 },
 {
  "name": " Ayesha Jehan",
  "id": "CZI-8030-2022"
 },
 {
  "name": " Alina Jawad",
  "id": "CVQ-8940-2022"
 },
 {
  "name": " Ahmad Javid",
  "id": "AAK-3233-2020"
 },
 {
  "name": " Sunia Javed",
  "id": "GXT-6734-2022"
 },
 {
  "name": " Kashif Javed",
  "id": "HNX-3216-2023"
 },
 {
  "name": " Kashif Javed",
  "id": "HQC-1973-2023"
 },
 {
  "name": " Aneela Javed",
  "id": "GCG-6302-2022"
 },
 {
  "name": " Ali Javed",
  "id": "HQA-1607-2023"
 },
 {
  "name": " Ahad Hussain Javed",
  "id": "DUU-3715-2022"
 },
 {
  "name": " Adeel Javed",
  "id": "CWS-6148-2022"
 },
 {
  "name": " Umer Javaid",
  "id": "HJC-8156-2022"
 },
 {
  "name": " Saba Javaid",
  "id": "GRL-0134-2022"
 },
 {
  "name": " Farhan Javaid",
  "id": "HDM-9760-2022"
 },
 {
  "name": " Aftab Javaid",
  "id": "GYZ-5160-2022"
 },
 {
  "name": " Ali Javadi-Abhari",
  "id": "GMP-7825-2022"
 },
 {
  "name": " Hussnain Ahmed Janjua",
  "id": "GLO-6550-2022"
 },
 {
  "name": " Abdul Rehman Janjua",
  "id": "FCU-5276-2022"
 },
 {
  "name": " Rahim Jan",
  "id": "GLO-5798-2022"
 },
 {
  "name": " Rahim Jan",
  "id": "HWC-9209-2023"
 },
 {
  "name": " S. Muhammad Jamil",
  "id": "EZD-2423-2022"
 },
 {
  "name": " Muhammad Jamil",
  "id": "DXC-2264-2022"
 },
 {
  "name": " Mubasher Jamil",
  "id": "M-2178-2015"
 },
 {
  "name": " M. Jamil",
  "id": "GBN-5305-2022"
 },
 {
  "name": " Faisal Jamil",
  "id": "ABC-7560-2020"
 },
 {
  "name": " Ahmad Jamil",
  "id": "FBF-3380-2022"
 },
 {
  "name": " Yousuf Jamal",
  "id": "FYR-0293-2022"
 },
 {
  "name": " Maira Jalil",
  "id": "HIK-7856-2022"
 },
 {
  "name": " Amna Jalil",
  "id": "EZN-9201-2022"
 },
 {
  "name": " Sidrah Jahangir",
  "id": "EZN-2833-2022"
 },
 {
  "name": " Muhammad Talha Jahangir",
  "id": "ILP-3756-2023"
 },
 {
  "name": " Maham Jahangir",
  "id": "CWY-6442-2022"
 },
 {
  "name": " Zaib Jahan",
  "id": "EZP-8750-2022"
 },
 {
  "name": " Turab H. Jafri",
  "id": "HKE-4222-2023"
 },
 {
  "name": " Syed Husain Imran Jaffery",
  "id": "AAB-1097-2022"
 },
 {
  "name": " Syed Hassan Abbas Jaffery",
  "id": "DXE-5708-2022"
 },
 {
  "name": " Maharij H. Jadoon",
  "id": "FBK-1236-2022"
 },
 {
  "name": " Warda Jabeen",
  "id": "HGN-7334-2022"
 },
 {
  "name": " Ishrat Jabeen",
  "id": "AAD-1389-2022"
 },
 {
  "name": " Farzana Jabeen",
  "id": "CWD-7817-2022"
 },
 {
  "name": " Fareeha Jabeen",
  "id": "CVV-7122-2022"
 },
 {
  "name": " Hamid Jabbar",
  "id": "I-4879-2015"
 },
 {
  "name": " Ghafirlia Istafa",
  "id": "HGX-6390-2022"
 },
 {
  "name": " Yasir Islam",
  "id": "FZT-7013-2022"
 },
 {
  "name": " Tanweer Islam",
  "id": "AAU-2748-2020"
 },
 {
  "name": " Muhammad Muzammal Islam",
  "id": "EYH-7235-2022"
 },
 {
  "name": " Sumaya Ishtiaq",
  "id": "GWG-6360-2022"
 },
 {
  "name": " Ayesha Ishfaq",
  "id": "CWE-6263-2022"
 },
 {
  "name": " N. Ishaque",
  "id": "GSC-4125-2022"
 },
 {
  "name": " Zaara Ishaq",
  "id": "FCA-2623-2022"
 },
 {
  "name": " Noaman Ishaq",
  "id": "CWH-9794-2022"
 },
 {
  "name": " Amna Ishaq",
  "id": "GPM-3597-2022"
 },
 {
  "name": " Sidra Irum",
  "id": "FBS-9755-2022"
 },
 {
  "name": " S. Irum",
  "id": "CVD-7437-2022"
 },
 {
  "name": " R. Irfan",
  "id": "FBF-6974-2022"
 },
 {
  "name": " Muhammad Irfan",
  "id": "GBT-0318-2022"
 },
 {
  "name": " Muhammad Irfan",
  "id": "HTH-4467-2023"
 },
 {
  "name": " Irfan Irfan",
  "id": "HTC-7865-2023"
 },
 {
  "name": " Irfan Irfan",
  "id": "CVG-6348-2022"
 },
 {
  "name": " Sadia Iram",
  "id": "EZG-6868-2022"
 },
 {
  "name": " Khushbakht Iqtidar",
  "id": "GCN-4359-2022"
 },
 {
  "name": " Maham Iqra",
  "id": "CVU-7308-2022"
 },
 {
  "name": " Yasir Iqbal",
  "id": "GNC-2386-2022"
 },
 {
  "name": " Tooba Iqbal",
  "id": "GBU-3080-2022"
 },
 {
  "name": " Taosif Iqbal",
  "id": "FAU-7277-2022"
 },
 {
  "name": " Talha Iqbal",
  "id": "GSL-9670-2022"
 },
 {
  "name": " Sohail Iqbal",
  "id": "DTW-1291-2022"
 },
 {
  "name": " Shahid Iqbal",
  "id": "J-1385-2016"
 },
 {
  "name": " Sajid Iqbal",
  "id": "DSZ-3508-2022"
 },
 {
  "name": " Saeed Iqbal",
  "id": "FZE-9810-2022"
 },
 {
  "name": " Rana Muhammad Arslan Iqbal",
  "id": "CWW-4925-2022"
 },
 {
  "name": " Rafia Iqbal",
  "id": "HIQ-3916-2022"
 },
 {
  "name": " Naveed Iqbal",
  "id": "HLS-9539-2023"
 },
 {
  "name": " Naseem Iqbal",
  "id": "AAE-8727-2021"
 },
 {
  "name": " Muhammad S. Iqbal",
  "id": "DUS-2795-2022"
 },
 {
  "name": " Muhammad Azhar Iqbal",
  "id": "HSB-0259-2023"
 },
 {
  "name": " Muhammad Iqbal",
  "id": "CWG-5490-2022"
 },
 {
  "name": " Mudassir Iqbal",
  "id": "HVB-0062-2023"
 },
 {
  "name": " Mudassir Iqbal",
  "id": "AAE-9249-2019"
 },
 {
  "name": " Mudassir Iqbal",
  "id": "GPS-7678-2022"
 },
 {
  "name": " Mudassir Iqbal",
  "id": "HLO-0614-2023"
 },
 {
  "name": " Mehwish Iqbal",
  "id": "FAA-7401-2022"
 },
 {
  "name": " M. S. Iqbal",
  "id": "HNT-2722-2023"
 },
 {
  "name": " M. Bilal Iqbal",
  "id": "CVY-8105-2022"
 },
 {
  "name": " Javed Iqbal",
  "id": "GXS-6611-2022"
 },
 {
  "name": " Hamid Iqbal",
  "id": "EZC-8085-2022"
 },
 {
  "name": " H. Iqbal",
  "id": "ILA-8331-2023"
 },
 {
  "name": " Arfa Iqbal",
  "id": "CVG-0700-2022"
 },
 {
  "name": " A. Iqbal",
  "id": "HHG-7020-2022"
 },
 {
  "name": " Muhammad Ali Inarn",
  "id": "GNR-7955-2022"
 },
 {
  "name": " Muhammad Inam",
  "id": "DTS-4195-2022"
 },
 {
  "name": " Umair Imtiaz",
  "id": "GMD-7939-2022"
 },
 {
  "name": " Maleeha Imtiaz",
  "id": "CVM-9013-2022"
 },
 {
  "name": " Beenish Imtiaz",
  "id": "EZH-4670-2022"
 },
 {
  "name": " M. Imranullah",
  "id": "CVP-8355-2022"
 },
 {
  "name": " Muhammad Imran",
  "id": "U-5544-2019"
 },
 {
  "name": " Muhammad Imran",
  "id": "DVW-8076-2022"
 },
 {
  "name": " Muhammad Imran",
  "id": "AAS-9984-2021"
 },
 {
  "name": " Kashif Imran",
  "id": "DVD-9329-2022"
 },
 {
  "name": " Hamza Ali Imran",
  "id": "ABD-1591-2020"
 },
 {
  "name": " Muhammad Ilyas",
  "id": "DWS-2185-2022"
 },
 {
  "name": " Israr Ilyas",
  "id": "FBH-3666-2022"
 },
 {
  "name": " Naima Iltaf",
  "id": "EYZ-0007-2022"
 },
 {
  "name": " M. Umair Illahi",
  "id": "GQI-5478-2022"
 },
 {
  "name": " Fizza Illahi",
  "id": "FDP-4450-2022"
 },
 {
  "name": " Muhammad Haris Ikram",
  "id": "EZK-3824-2022"
 },
 {
  "name": " Musfirah Ihtasham",
  "id": "HLA-0630-2023"
 },
 {
  "name": " Sara Iftikhar",
  "id": "CVH-7743-2022"
 },
 {
  "name": " M. A. Iftikhar",
  "id": "IEO-8298-2023"
 },
 {
  "name": " Kinza Iftikhar",
  "id": "GZC-9596-2022"
 },
 {
  "name": " Zahid Ifrah",
  "id": "EZM-3120-2022"
 },
 {
  "name": " Shafaq Idrees",
  "id": "FCK-2307-2022"
 },
 {
  "name": " Saad Idrees",
  "id": "FCJ-2363-2022"
 },
 {
  "name": " Muhammad Idrees",
  "id": "GFO-5404-2022"
 },
 {
  "name": " Muhammad Idrees",
  "id": "HGT-6691-2022"
 },
 {
  "name": " Hassaan Idrees",
  "id": "FCM-0881-2022"
 },
 {
  "name": " Gul I hina Aslam",
  "id": "FYV-2993-2022"
 },
 {
  "name": " Zakir Hussain",
  "id": "GPJ-8866-2022"
 },
 {
  "name": " Wajahat Hussain",
  "id": "HIF-4427-2022"
 },
 {
  "name": " Syed Waqas Hussain",
  "id": "FDK-1621-2022"
 },
 {
  "name": " Shahid Hussain",
  "id": "CWS-7724-2022"
 },
 {
  "name": " Saqib Hussain",
  "id": "GSF-3959-2022"
 },
 {
  "name": " S. T. Hussain",
  "id": "EZY-9762-2022"
 },
 {
  "name": " Naveed Hussain",
  "id": "DVL-9984-2022"
 },
 {
  "name": " Mehdi Hussain",
  "id": "FCT-3277-2022"
 },
 {
  "name": " Mehdi Hussain",
  "id": "DUC-5937-2022"
 },
 {
  "name": " Manzoor Hussain",
  "id": "CXL-1882-2022"
 },
 {
  "name": " Manzoor Hussain",
  "id": "DVX-0913-2022"
 },
 {
  "name": " M. S. Hussain",
  "id": "FYN-6525-2022"
 },
 {
  "name": " Kazmi Sayed Tassawar Hussain",
  "id": "EZX-1847-2022"
 },
 {
  "name": " Hamza Hussain",
  "id": "EZY-6536-2022"
 },
 {
  "name": " Farhan Hussain",
  "id": "FAM-4965-2022"
 },
 {
  "name": " Danish Hussain",
  "id": "ILQ-6085-2023"
 },
 {
  "name": " Danish Hussain",
  "id": "FYI-4840-2022"
 },
 {
  "name": " Bilawal Hussain",
  "id": "CXR-7674-2022"
 },
 {
  "name": " Arshad Hussain",
  "id": "IAC-9576-2023"
 },
 {
  "name": " Anwar Hussain",
  "id": "HJF-0672-2022"
 },
 {
  "name": " Asif Hussain Khoja",
  "id": "J-6473-2015"
 },
 {
  "name": " Aliya Hisam",
  "id": "GCG-3181-2022"
 },
 {
  "name": " Syed Fahad Hassany",
  "id": "GRZ-2806-2022"
 },
 {
  "name": " Zohaib Hassan",
  "id": "CVC-7947-2022"
 },
 {
  "name": " Syed Ali Hassan",
  "id": "C-1413-2017"
 },
 {
  "name": " Sadia Hassan",
  "id": "CSS-0625-2022"
 },
 {
  "name": " Rabia Hassan",
  "id": "EYQ-1626-2022"
 },
 {
  "name": " Muneeb Hassan",
  "id": "CTS-8578-2022"
 },
 {
  "name": " Muhammad Usman Hassan",
  "id": "IEG-2187-2023"
 },
 {
  "name": " Muhammad Sabbar Hassan",
  "id": "IDC-6313-2023"
 },
 {
  "name": " Muhammad Hassan",
  "id": "FAZ-5242-2022"
 },
 {
  "name": " Muhammad Hassan",
  "id": "FAC-3332-2022"
 },
 {
  "name": " Moez ul Hassan",
  "id": "IQT-3208-2023"
 },
 {
  "name": " Ali Hassan",
  "id": "DVP-2445-2022"
 },
 {
  "name": " Ahmad Hassan",
  "id": "GMU-0748-2022"
 },
 {
  "name": " Muhammad Hassaan",
  "id": "EWP-7247-2022"
 },
 {
  "name": " Umair Sajid Hasmi",
  "id": "GOZ-8126-2022"
 },
 {
  "name": " Umair Sajid Hashmi",
  "id": "CVB-0763-2022"
 },
 {
  "name": " Sidra Hashmi",
  "id": "GMY-0584-2022"
 },
 {
  "name": " Sakina Hashmi",
  "id": "HHG-3259-2022"
 },
 {
  "name": " Imran Hashmi",
  "id": "HFS-1784-2022"
 },
 {
  "name": " Fahim Hashmi",
  "id": "CVX-3480-2022"
 },
 {
  "name": " Ehsan Mustafa Hashmi",
  "id": "GPD-7812-2022"
 },
 {
  "name": " Atta ul Mannan Hashmi",
  "id": "HDR-5892-2022"
 },
 {
  "name": " Osman Hasan",
  "id": "GAJ-4800-2022"
 },
 {
  "name": " Azhar Hasan",
  "id": "CTP-7086-2022"
 },
 {
  "name": " Ammar Hasan",
  "id": "IEG-7236-2023"
 },
 {
  "name": " Ammar Hasan",
  "id": "CTR-4428-2022"
 },
 {
  "name": " Wajiha Haq",
  "id": "AAE-7588-2021"
 },
 {
  "name": " Rizwan Haq",
  "id": "GAJ-8014-2022"
 },
 {
  "name": " N. U. Haq",
  "id": "FBW-8544-2022"
 },
 {
  "name": " Ihsan Ul Haq",
  "id": "GRZ-9461-2022"
 },
 {
  "name": " Hina Binte Haq",
  "id": "CSK-6738-2022"
 },
 {
  "name": " Uzma Hanif",
  "id": "DWR-6737-2022"
 },
 {
  "name": " Rumeza Hanif",
  "id": "EXA-8628-2022"
 },
 {
  "name": " Naeema Hanif",
  "id": "CUG-5100-2022"
 },
 {
  "name": " Ali Hanif",
  "id": "GCH-3190-2022"
 },
 {
  "name": " Mobeen Haneef",
  "id": "DVF-0658-2022"
 },
 {
  "name": " Mahnoor Hamza",
  "id": "GOL-2077-2022"
 },
 {
  "name": " Ameer Hamza",
  "id": "HME-9461-2023"
 },
 {
  "name": " Rana Hammad Raza",
  "id": "FSZ-6964-2022"
 },
 {
  "name": " Maryam Hamid",
  "id": "GUJ-4932-2022"
 },
 {
  "name": " Nasir Hameed",
  "id": "GDA-5231-2022"
 },
 {
  "name": " Asad Hameed",
  "id": "ABI-3306-2020"
 },
 {
  "name": " Syeda Fizza Hamdani",
  "id": "GXB-8689-2022"
 },
 {
  "name": " Syed Wasif Abbas Hamdani",
  "id": "DUM-8869-2022"
 },
 {
  "name": " Noor Haleem",
  "id": "GSE-5518-2022"
 },
 {
  "name": " Muhammad Waqas Hakim",
  "id": "HNI-7313-2023"
 },
 {
  "name": " Arhum Hakim",
  "id": "HIW-3931-2022"
 },
 {
  "name": " Zulqarnain Haider",
  "id": "H-4809-2019"
 },
 {
  "name": " Usman A. Haider",
  "id": "IMD-1131-2023"
 },
 {
  "name": " Syed Altan Haider",
  "id": "DXT-0822-2022"
 },
 {
  "name": " Sajjad Haider",
  "id": "HKS-2529-2023"
 },
 {
  "name": " Qurrat-ul-Ain Haider",
  "id": "CTK-0059-2022"
 },
 {
  "name": " Ghulam Haider",
  "id": "AAF-3457-2020"
 },
 {
  "name": " Ali Haider",
  "id": "HDO-5956-2022"
 },
 {
  "name": " Abbas Haider",
  "id": "GRX-6701-2022"
 },
 {
  "name": " Sumaira Hafeez",
  "id": "CSC-1152-2022"
 },
 {
  "name": " Hamza Hafeez",
  "id": "FBH-5369-2022"
 },
 {
  "name": " Imran Hafeez Abbassi",
  "id": "EJF-0908-2022"
 },
 {
  "name": " Marva Hadia",
  "id": "HNT-1669-2023"
 },
 {
  "name": " Shahzaib Farooq Hadi",
  "id": "CSR-7396-2022"
 },
 {
  "name": " Zunaira Habib",
  "id": "EYS-6192-2022"
 },
 {
  "name": " Uzma Habib",
  "id": "ABB-7637-2020"
 },
 {
  "name": " Muzaffar Habib",
  "id": "GLZ-4383-2022"
 },
 {
  "name": " Hassan Habib",
  "id": "CTV-5676-2022"
 },
 {
  "name": " WAQAS HASSAN",
  "id": "HZM-5536-2023"
 },
 {
  "name": " QAZI MAZHAR UL HAQ",
  "id": "AEJ-5807-2022"
 },
 {
  "name": " IMRAN HAIDER",
  "id": "F-1479-2018"
 },
 {
  "name": " Asma Gulzar",
  "id": "EZB-1943-2022"
 },
 {
  "name": " Rameesha Gull",
  "id": "GMD-8767-2022"
 },
 {
  "name": " Shabana Gul",
  "id": "CUO-9420-2022"
 },
 {
  "name": " Saba Gul",
  "id": "DSU-5218-2022"
 },
 {
  "name": " Jawad Gul",
  "id": "GOL-4908-2022"
 },
 {
  "name": " Iftikhar Hussain Gul",
  "id": "EXO-4236-2022"
 },
 {
  "name": " Ifra Fiaz Gul",
  "id": "IEC-6739-2023"
 },
 {
  "name": " Hashmat Gul",
  "id": "EXD-1535-2022"
 },
 {
  "name": " Banat Gul",
  "id": "DVZ-5379-2022"
 },
 {
  "name": " Alvina Gul",
  "id": "Z-4497-2019"
 },
 {
  "name": " Alvina Gul",
  "id": "GEU-6843-2022"
 },
 {
  "name": " Miriam K. Gomez",
  "id": "CSJ-0688-2022"
 },
 {
  "name": " Hamad Gohar",
  "id": "GPO-1791-2022"
 },
 {
  "name": " Syed Omer Gilani",
  "id": "DXO-2328-2022"
 },
 {
  "name": " Syed Omer Gilani",
  "id": "AAH-6237-2019"
 },
 {
  "name": " Mehwish Gilani",
  "id": "CRQ-9370-2022"
 },
 {
  "name": " Usman Ghumman",
  "id": "CSO-0273-2022"
 },
 {
  "name": " Maria Ghufran",
  "id": "GOZ-0766-2022"
 },
 {
  "name": " Fareeha Khalid Ghori",
  "id": "GOP-7094-2022"
 },
 {
  "name": " Uzma Ghani",
  "id": "HTW-8345-2023"
 },
 {
  "name": " Shahbaz Ghani",
  "id": "HFD-0735-2022"
 },
 {
  "name": " Umar Ghafoor",
  "id": "EUW-9902-2022"
 },
 {
  "name": " Salman Ghafoor",
  "id": "AAT-8792-2021"
 },
 {
  "name": " Muhammad Fazeel Ghafoor",
  "id": "GQK-8415-2022"
 },
 {
  "name": " Bakhtawar Ghafoor",
  "id": "CRS-3028-2022"
 },
 {
  "name": " Abdul Ghafoor",
  "id": "HDK-1606-2022"
 },
 {
  "name": " Ali Ghaffari",
  "id": "CBM-8016-2022"
 },
 {
  "name": " Hamza Farooq Gabriel",
  "id": "W-8334-2018"
 },
 {
  "name": " Rabeeka Firdous",
  "id": "EVA-4054-2022"
 },
 {
  "name": " Tooba Feroze",
  "id": "GFX-4118-2022"
 },
 {
  "name": " Dilaawaiz Fazal",
  "id": "T-9834-2019"
 },
 {
  "name": " Misha Fatima",
  "id": "EUD-3762-2022"
 },
 {
  "name": " Maha Fatima",
  "id": "HNY-0380-2023"
 },
 {
  "name": " Howra Fatima",
  "id": "HIV-6673-2022"
 },
 {
  "name": " G. Fatima",
  "id": "COV-6738-2022"
 },
 {
  "name": " Baheesa Fatima",
  "id": "GMQ-3962-2022"
 },
 {
  "name": " Anum Fatima",
  "id": "DXG-0108-2022"
 },
 {
  "name": " Muhammad Ashfaq Fasih",
  "id": "GMJ-6863-2022"
 },
 {
  "name": " M. Saad Fasih",
  "id": "HGL-4702-2022"
 },
 {
  "name": " Asma Faryal",
  "id": "HIV-7518-2022"
 },
 {
  "name": " Sarah Farukkh",
  "id": "GOH-6627-2022"
 },
 {
  "name": " Sarah Farrukh",
  "id": "AAJ-3285-2020"
 },
 {
  "name": " Tayyaba Farooqi",
  "id": "EUO-9552-2022"
 },
 {
  "name": " Mahrukh Farooqi",
  "id": "CNZ-0019-2022"
 },
 {
  "name": " Syed Hassan Farooq",
  "id": "HSJ-6677-2023"
 },
 {
  "name": " Syed Hassan Farooq",
  "id": "DTG-3432-2022"
 },
 {
  "name": " Sara Farooq",
  "id": "EUO-9270-2022"
 },
 {
  "name": " Rashid Farooq",
  "id": "EWO-9149-2022"
 },
 {
  "name": " Muhammad Umar Farooq",
  "id": "IPI-0083-2023"
 },
 {
  "name": " Muhammad Siddique Farooq",
  "id": "HAK-6163-2022"
 },
 {
  "name": " Muhammad Asif Farooq",
  "id": "W-6601-2019"
 },
 {
  "name": " Muhammad Ansar Farooq",
  "id": "AAB-7061-2019"
 },
 {
  "name": " Shanza Faridi",
  "id": "ESD-5391-2022"
 },
 {
  "name": " Kulsoom Farhat",
  "id": "ETR-5631-2022"
 },
 {
  "name": " Kunwar Faraz",
  "id": "CPS-5079-2022"
 },
 {
  "name": " Ahmed Faraz",
  "id": "EWX-3599-2022"
 },
 {
  "name": " Christian Falconi",
  "id": "T-7369-2017"
 },
 {
  "name": " Umair Fakhar",
  "id": "GZI-5175-2022"
 },
 {
  "name": " Faiz Faizullah",
  "id": "DYH-3397-2022"
 },
 {
  "name": " Sohaib Faiz",
  "id": "GTG-8725-2022"
 },
 {
  "name": " Faizullah Faiz",
  "id": "GMD-8041-2022"
 },
 {
  "name": " Elizbit",
  "id": "EVN-0490-2022"
 },
 {
  "name": " Waqas Ejaz",
  "id": "FXT-6735-2022"
 },
 {
  "name": " Waqas Ejaz",
  "id": "GQA-5508-2022"
 },
 {
  "name": " Sidra Ejaz",
  "id": "CPE-7281-2022"
 },
 {
  "name": " Saima Ejaz",
  "id": "CNY-4586-2022"
 },
 {
  "name": " Kanwal Ejaz",
  "id": "CPI-8000-2022"
 },
 {
  "name": " Ali Ejaz",
  "id": "CNO-8364-2022"
 },
 {
  "name": " Ebadat-ur-Rehman",
  "id": "IHG-3867-2023"
 },
 {
  "name": " Hina M. Dutt",
  "id": "COV-5952-2022"
 },
 {
  "name": " Inamullah Douna",
  "id": "DWS-2136-2022"
 },
 {
  "name": " Hassan Mohy Ud Din",
  "id": "GMJ-6622-2022"
 },
 {
  "name": " Emad Ud Din",
  "id": "DYV-1799-2022"
 },
 {
  "name": " Sania Dawood",
  "id": "GWT-8155-2022"
 },
 {
  "name": " Naveed Ahmad Chughtai",
  "id": "GBM-7929-2022"
 },
 {
  "name": " Hasan Qayyum Chohan",
  "id": "EQY-6853-2022"
 },
 {
  "name": " Muhammad Ilyas Chishti",
  "id": "AHA-4220-2022"
 },
 {
  "name": " Kudakwashe Chirambwi",
  "id": "CKT-2202-2022"
 },
 {
  "name": " Muhammad Asaad Cheema",
  "id": "EPG-5079-2022"
 },
 {
  "name": " Alina Chaudhry",
  "id": "CJB-1207-2022"
 },
 {
  "name": " Wasi Haider Butt",
  "id": "AAH-8517-2019"
 },
 {
  "name": " Shadab Ahmed Butt",
  "id": "CGT-4755-2022"
 },
 {
  "name": " Sajid Ullah Butt",
  "id": "DSX-1982-2022"
 },
 {
  "name": " S. U. Butt",
  "id": "CIJ-0757-2022"
 },
 {
  "name": " S. I. Butt",
  "id": "DWH-5213-2022"
 },
 {
  "name": " Rohan Zafar Butt",
  "id": "CJG-5210-2022"
 },
 {
  "name": " Hammad Tanveer Butt",
  "id": "DUM-8494-2022"
 },
 {
  "name": " Fahad Rafi Butt",
  "id": "CHV-2874-2022"
 },
 {
  "name": " Jehanzeb Burki",
  "id": "ENN-3737-2022"
 },
 {
  "name": " Saima Bukhat Khan",
  "id": "CXR-6637-2022"
 },
 {
  "name": " Syeda Aqsa Batool Bukhari",
  "id": "CGH-6190-2022"
 },
 {
  "name": " Syed Basit Ali Bukhari",
  "id": "I-3751-2019"
 },
 {
  "name": " H. Bukhari",
  "id": "ENL-7299-2022"
 },
 {
  "name": " Hadia Bint Monir",
  "id": "IGJ-5547-2023"
 },
 {
  "name": " Haris Bin Tanveer",
  "id": "CGJ-1834-2022"
 },
 {
  "name": " Waleed Bin Shahid",
  "id": "GBK-9973-2022"
 },
 {
  "name": " Muhammad Taha Bin Owais",
  "id": "CFH-8018-2022"
 },
 {
  "name": " Shah Fahad Bin Masud",
  "id": "EOG-1519-2022"
 },
 {
  "name": " Muhammad Usmaan Bin Khawer",
  "id": "GXD-8322-2022"
 },
 {
  "name": " Saad Bin Khalid",
  "id": "EMX-8716-2022"
 },
 {
  "name": " Mojeeb Bin Ihsan",
  "id": "CEQ-0696-2022"
 },
 {
  "name": " Zaeem Bin Baber",
  "id": "GLW-3256-2022"
 },
 {
  "name": " Zaeem Bin Babar",
  "id": "T-1026-2019"
 },
 {
  "name": " Zaeem Bin Babar",
  "id": "DUX-4470-2022"
 },
 {
  "name": " Muhammad Bin Azhar",
  "id": "GYK-5451-2022"
 },
 {
  "name": " Anas Bin Aqeel",
  "id": "ABH-8359-2020"
 },
 {
  "name": " M. Zain Bin Amjad",
  "id": "FXE-2689-2022"
 },
 {
  "name": " Namra Bilal",
  "id": "HOQ-8904-2023"
 },
 {
  "name": " Muhammad Bilal",
  "id": "DTO-0795-2022"
 },
 {
  "name": " Muhammad Bilal",
  "id": "ELC-7430-2022"
 },
 {
  "name": " Naseeha Bibi",
  "id": "EMG-1601-2022"
 },
 {
  "name": " Rai Salaar Sultan Bhatti",
  "id": "HSL-5827-2023"
 },
 {
  "name": " Muhammad Faraz Bhatti",
  "id": "FZV-5142-2022"
 },
 {
  "name": " Iram Tariq Bhatti",
  "id": "EPN-8508-2022"
 },
 {
  "name": " Attya Bhatti",
  "id": "HTT-9426-2023"
 },
 {
  "name": " Attya Bhatti",
  "id": "GEC-6992-2022"
 },
 {
  "name": " Ali Hussain Umar Bhatti",
  "id": "ABE-6386-2021"
 },
 {
  "name": " Bilal Beig",
  "id": "CDQ-8821-2022"
 },
 {
  "name": " Uzma Batool",
  "id": "HGB-8303-2022"
 },
 {
  "name": " T. S. Batool",
  "id": "ENA-8476-2022"
 },
 {
  "name": " Sammana Batool",
  "id": "GAQ-7805-2022"
 },
 {
  "name": " Samera Batool",
  "id": "DTW-7645-2022"
 },
 {
  "name": " Sahar Batool",
  "id": "EMV-1978-2022"
 },
 {
  "name": " Sadaf Batool",
  "id": "FZV-1556-2022"
 },
 {
  "name": " Farhat Batool",
  "id": "EOF-5398-2022"
 },
 {
  "name": " Maryam Basit",
  "id": "FZD-1832-2022"
 },
 {
  "name": " Rabeea Basir",
  "id": "CDH-3716-2022"
 },
 {
  "name": " Shanza Bashir",
  "id": "GRE-7639-2022"
 },
 {
  "name": " Muhammad Arslan Bashir",
  "id": "IBX-2102-2023"
 },
 {
  "name": " Sarah Basharat",
  "id": "AAC-8016-2022"
 },
 {
  "name": " Aamer Ahmed Baqai",
  "id": "EKV-0176-2022"
 },
 {
  "name": " Kanwal Bansari",
  "id": "CYN-0152-2022"
 },
 {
  "name": " Tehzeeb Bano",
  "id": "EJY-9450-2022"
 },
 {
  "name": " Zafar Bangash",
  "id": "CFT-9984-2022"
 },
 {
  "name": " Yawar Abbas Bangash",
  "id": "CDJ-3973-2022"
 },
 {
  "name": " Sanam Banaras",
  "id": "GRK-6624-2022"
 },
 {
  "name": " Mahnoor Baloch",
  "id": "EMO-5015-2022"
 },
 {
  "name": " Jibran Baloch",
  "id": "GZC-1494-2022"
 },
 {
  "name": " Babar A. Baloch",
  "id": "GNR-0644-2022"
 },
 {
  "name": " Asim D. Bakhshi",
  "id": "AAZ-1697-2020"
 },
 {
  "name": " Tariq Mahmood Bajwa",
  "id": "EKM-5082-2022"
 },
 {
  "name": " Zunaira Ali Baig",
  "id": "GMJ-1462-2022"
 },
 {
  "name": " Shahbaz Baig",
  "id": "AAX-9652-2020"
 },
 {
  "name": " Mutawara Baig",
  "id": "ABB-9460-2020"
 },
 {
  "name": " Yasmin Badshah",
  "id": "FZR-4643-2022"
 },
 {
  "name": " Sufian A. Badawi",
  "id": "CEH-2992-2022"
 },
 {
  "name": " Zunaira Badar",
  "id": "GLW-5528-2022"
 },
 {
  "name": " Maria Badar",
  "id": "FZP-3148-2022"
 },
 {
  "name": " Muhammad Zafarullah Baber",
  "id": "EMA-3500-2022"
 },
 {
  "name": " Ahmad Jamal Baber",
  "id": "CEI-2453-2022"
 },
 {
  "name": " Zainab Babar",
  "id": "GUG-3629-2022"
 },
 {
  "name": " Zaeem Bin Babar",
  "id": "EMB-0480-2022"
 },
 {
  "name": " Sumbal Babar",
  "id": "CCX-2271-2022"
 },
 {
  "name": " M. Azmat",
  "id": "HJX-1769-2023"
 },
 {
  "name": " Ubair Aziz",
  "id": "HEZ-5516-2022"
 },
 {
  "name": " Talha Aziz",
  "id": "CDW-5472-2022"
 },
 {
  "name": " Humaira Aziz",
  "id": "ELJ-1522-2022"
 },
 {
  "name": " Asim Aziz",
  "id": "FWV-6642-2022"
 },
 {
  "name": " Aesar Aziz",
  "id": "GMQ-5076-2022"
 },
 {
  "name": " R. A. Azim",
  "id": "CEA-0325-2022"
 },
 {
  "name": " Shabia Azhar",
  "id": "ELI-3620-2022"
 },
 {
  "name": " Rimsha Azhar",
  "id": "EOP-4352-2022"
 },
 {
  "name": " Nikhar Azhar",
  "id": "GYE-8822-2022"
 },
 {
  "name": " J Azhar",
  "id": "EML-8144-2022"
 },
 {
  "name": " Anique Azhar",
  "id": "ELZ-8603-2022"
 },
 {
  "name": " A. Azhar",
  "id": "CEF-2828-2022"
 },
 {
  "name": " Muhammad Kashif Azeem",
  "id": "GCV-4378-2022"
 },
 {
  "name": " Usama Azam",
  "id": "CEO-1015-2022"
 },
 {
  "name": " Farooque Azam",
  "id": "HWV-9782-2023"
 },
 {
  "name": " Fahad Azad",
  "id": "AAF-7264-2019"
 },
 {
  "name": " Fahad Aza",
  "id": "CEN-4781-2022"
 },
 {
  "name": " Saqib Ayuob",
  "id": "GYK-7278-2022"
 },
 {
  "name": " Atif Ayub",
  "id": "ENI-1238-2022"
 },
 {
  "name": " Mariam Ayesha",
  "id": "EJS-2521-2022"
 },
 {
  "name": " Muhammad Amjad Awan",
  "id": "AAJ-6919-2020"
 },
 {
  "name": " Hamad Hassan Awan",
  "id": "CCX-2119-2022"
 },
 {
  "name": " Muhammad Awais",
  "id": "DTZ-4598-2022"
 },
 {
  "name": " Yasar Avaz",
  "id": "GSC-1236-2022"
 },
 {
  "name": " Haris Ataullah",
  "id": "GRO-8332-2022"
 },
 {
  "name": " Nausheen Ata",
  "id": "CEB-5502-2022"
 },
 {
  "name": " Tehreem Aslam",
  "id": "CEN-0685-2022"
 },
 {
  "name": " Muhammad Mubashar Aslam",
  "id": "ICB-3051-2023"
 },
 {
  "name": " Jawad Aslam",
  "id": "HXV-6596-2023"
 },
 {
  "name": " Ch Muhammad Afaq Aslam",
  "id": "EMJ-1766-2022"
 },
 {
  "name": " Baber Aslam",
  "id": "EJY-0570-2022"
 },
 {
  "name": " Ayman Aslam",
  "id": "EMJ-7668-2022"
 },
 {
  "name": " Adnan Aslam",
  "id": "DTZ-3642-2022"
 },
 {
  "name": " Farhat Asim",
  "id": "GLV-8439-2022"
 },
 {
  "name": " Muhammad Asif",
  "id": "DSX-9135-2022"
 },
 {
  "name": " Muhammad Asif",
  "id": "AAC-8362-2022"
 },
 {
  "name": " Mansoor Asif",
  "id": "ENQ-3921-2022"
 },
 {
  "name": " Wahab Ashraf",
  "id": "EKY-9580-2022"
 },
 {
  "name": " Tabinda Ashraf",
  "id": "CEF-9819-2022"
 },
 {
  "name": " Nausheen Ashraf",
  "id": "EOR-0067-2022"
 },
 {
  "name": " Muhammad Mubashar Ashraf",
  "id": "IAX-9085-2023"
 },
 {
  "name": " Muhammad Abaid Ashraf",
  "id": "CEH-9223-2022"
 },
 {
  "name": " Muhammad Ashraf",
  "id": "IJZ-7274-2023"
 },
 {
  "name": " Iffat Ashraf",
  "id": "CBZ-8613-2022"
 },
 {
  "name": " Zarlish Ashfaq",
  "id": "CEC-9070-2022"
 },
 {
  "name": " Muhammad Hamza Ashan",
  "id": "CDZ-9772-2022"
 },
 {
  "name": " Umer Asgher",
  "id": "K-2072-2012"
 },
 {
  "name": " Rai Asghar",
  "id": "CCI-5685-2022"
 },
 {
  "name": " Nimra Sher Asghar",
  "id": "GZC-2355-2022"
 },
 {
  "name": " Muhammad Asad Asghar",
  "id": "IKB-2159-2023"
 },
 {
  "name": " Mehmood Asghar",
  "id": "DVP-5934-2022"
 },
 {
  "name": " Samsaam uddin Asad",
  "id": "GNL-7160-2022"
 },
 {
  "name": " Muhammad Asad",
  "id": "IAF-6642-2023"
 },
 {
  "name": " Rao Arslan",
  "id": "GZK-9876-2022"
 },
 {
  "name": " Muhammad Arslan Zahid",
  "id": "IIS-1004-2023"
 },
 {
  "name": " Ghulam Arshed",
  "id": "CEH-0037-2022"
 },
 {
  "name": " Syeda Rabia Arshad",
  "id": "GMJ-4832-2022"
 },
 {
  "name": " Syed Muhammad Nashit Arshad",
  "id": "EKX-1940-2022"
 },
 {
  "name": " S. Arshad",
  "id": "EJN-6280-2022"
 },
 {
  "name": " Ramsha Arshad",
  "id": "CDM-7910-2022"
 },
 {
  "name": " Muhammad Arshad",
  "id": "F-4922-2012"
 },
 {
  "name": " Muhammad Arshad",
  "id": "ELQ-2328-2022"
 },
 {
  "name": " Muhammad Arshad",
  "id": "IBA-3093-2023"
 },
 {
  "name": " Muhammad Arshad",
  "id": "IIT-0433-2023"
 },
 {
  "name": " Muhammad Armaghan",
  "id": "CDL-4517-2022"
 },
 {
  "name": " Wafa Arif",
  "id": "HKO-7372-2023"
 },
 {
  "name": " Usama Arif",
  "id": "EMF-7788-2022"
 },
 {
  "name": " Saad Arif",
  "id": "GRJ-0945-2022"
 },
 {
  "name": " Omar Arif",
  "id": "DWV-1966-2022"
 },
 {
  "name": " Muhammad Z. Arif",
  "id": "HKQ-3110-2023"
 },
 {
  "name": " Muhammad Naveed Arif",
  "id": "IIW-1697-2023"
 },
 {
  "name": " Muhammad Arif",
  "id": "EJK-2892-2022"
 },
 {
  "name": " Hajira Arif",
  "id": "GXP-4615-2022"
 },
 {
  "name": " Fahim Arif",
  "id": "CDN-5615-2022"
 },
 {
  "name": " Dooa Arif",
  "id": "EKP-5041-2022"
 },
 {
  "name": " Arshia Arif",
  "id": "CDZ-8620-2022"
 },
 {
  "name": " Muhammad Arfan",
  "id": "AAE-9737-2019"
 },
 {
  "name": " Jamshid Ardalankia",
  "id": "CWL-0465-2022"
 },
 {
  "name": " Haziq Arbab",
  "id": "GWF-5334-2022"
 },
 {
  "name": " A. B. Aqeel",
  "id": "CDV-9378-2022"
 },
 {
  "name": " A. Aqdas",
  "id": "EKK-6335-2022"
 },
 {
  "name": " Tayyaba Anwer",
  "id": "HGQ-7053-2022"
 },
 {
  "name": " Hassan Anwer",
  "id": "M-6118-2019"
 },
 {
  "name": " F. Anwer",
  "id": "EKS-1442-2022"
 },
 {
  "name": " Tahira Anwar",
  "id": "HND-8862-2023"
 },
 {
  "name": " Sidra Anwar",
  "id": "CDT-0217-2022"
 },
 {
  "name": " Mustafa Anwar",
  "id": "D-7815-2015"
 },
 {
  "name": " Muhammad Khalid Anwar",
  "id": "EKK-0305-2022"
 },
 {
  "name": " Matloob Anwar",
  "id": "CCS-7164-2022"
 },
 {
  "name": " Hirra Anwar",
  "id": "CBY-1073-2022"
 },
 {
  "name": " F. Anwar",
  "id": "EJY-1248-2022"
 },
 {
  "name": " Umar Ansari",
  "id": "EKA-8875-2022"
 },
 {
  "name": " Arfa Ansari",
  "id": "EKM-9911-2022"
 },
 {
  "name": " Abeera Ayaz Ansari",
  "id": "HWR-3125-2023"
 },
 {
  "name": " Abeera Ayaz Ansari",
  "id": "EKX-8704-2022"
 },
 {
  "name": " Saiqa Anjum",
  "id": "HFA-3332-2022"
 },
 {
  "name": " Muhammad Latif Anjum",
  "id": "DVM-2682-2022"
 },
 {
  "name": " Mahnoor Anjum",
  "id": "GBH-8203-2022"
 },
 {
  "name": " M. Shehzaib Anjum",
  "id": "HTX-4641-2023"
 },
 {
  "name": " Nerio Andres Montoya",
  "id": "FNY-1092-2022"
 },
 {
  "name": " Saadia Andleeb",
  "id": "EJM-5136-2022"
 },
 {
  "name": " Ali Ammar",
  "id": "HLJ-8613-2023"
 },
 {
  "name": " Shehzad Amjad",
  "id": "EMC-8029-2022"
 },
 {
  "name": " Muhammad M. Amjad",
  "id": "CBN-3412-2022"
 },
 {
  "name": " Muhammad Amjad",
  "id": "AAW-7888-2021"
 },
 {
  "name": " Faiqa Amjad",
  "id": "GMQ-0987-2022"
 },
 {
  "name": " Rabia Amir",
  "id": "EKO-0151-2022"
 },
 {
  "name": " Naila Amir",
  "id": "CCQ-7654-2022"
 },
 {
  "name": " Fawad Amin",
  "id": "GNA-0890-2022"
 },
 {
  "name": " Faheem Amin",
  "id": "W-6958-2019"
 },
 {
  "name": " Faheem Amin",
  "id": "ELI-8350-2022"
 },
 {
  "name": " Ameer Amin",
  "id": "ELE-5221-2022"
 },
 {
  "name": " Sanila Amber",
  "id": "AAQ-6992-2020"
 },
 {
  "name": " Shahzad Alvi",
  "id": "AAN-1234-2020"
 },
 {
  "name": " Shahzad Alvi",
  "id": "J-9479-2019"
 },
 {
  "name": " Noor Alvi",
  "id": "EJO-4175-2022"
 },
 {
  "name": " Sikandar Altaf",
  "id": "GVT-3458-2022"
 },
 {
  "name": " Sohaib Bin Altaf Khattak",
  "id": "CCI-0618-2022"
 },
 {
  "name": " Badee Alshameri",
  "id": "T-4883-2019"
 },
 {
  "name": " Adham Mohammed Alnadish",
  "id": "HGV-0392-2022"
 },
 {
  "name": " Zahoor Ahmed Alizai",
  "id": "DRO-2038-2022"
 },
 {
  "name": " Zeeshan Ali",
  "id": "AAF-6139-2019"
 },
 {
  "name": " Yasir Ali",
  "id": "AAV-1812-2020"
 },
 {
  "name": " Usman Ali",
  "id": "HJN-1435-2023"
 },
 {
  "name": " Syed Humair Ali",
  "id": "EJV-0013-2022"
 },
 {
  "name": " Syed Haider Ali",
  "id": "CBA-0285-2022"
 },
 {
  "name": " Shabana Ali",
  "id": "CBE-7261-2022"
 },
 {
  "name": " Sara Ali",
  "id": "ABC-9062-2020"
 },
 {
  "name": " Salman Ali",
  "id": "HVL-3054-2023"
 },
 {
  "name": " Sadaqat Ali",
  "id": "HSI-6678-2023"
 },
 {
  "name": " Sadaqat Ali",
  "id": "FWZ-4353-2022"
 },
 {
  "name": " Nihad Ali",
  "id": "HWZ-3492-2023"
 },
 {
  "name": " Murtaza Najabat Ali",
  "id": "GWE-5409-2022"
 },
 {
  "name": " Muhammad Ali",
  "id": "CCO-3553-2022"
 },
 {
  "name": " Muhammad Ali",
  "id": "CAZ-3987-2022"
 },
 {
  "name": " Muhammad Ali",
  "id": "IIY-6638-2023"
 },
 {
  "name": " Muddasir Ali",
  "id": "L-7903-2019"
 },
 {
  "name": " Mudassar Ali",
  "id": "DWO-2825-2022"
 },
 {
  "name": " Maryum Ali",
  "id": "CCA-9005-2022"
 },
 {
  "name": " Majid Ali",
  "id": "CBA-4134-2022"
 },
 {
  "name": " Hasnain Ali",
  "id": "GWA-2202-2022"
 },
 {
  "name": " Haseeb Ali",
  "id": "GNM-6348-2022"
 },
 {
  "name": " Elia Nauroz Ali",
  "id": "GOP-6409-2022"
 },
 {
  "name": " Asher Ali",
  "id": "GMQ-1785-2022"
 },
 {
  "name": " Asghar Ali",
  "id": "CBG-1374-2022"
 },
 {
  "name": " Asghar Ali",
  "id": "EMJ-6080-2022"
 },
 {
  "name": " Amjad Ali",
  "id": "AAG-4441-2021"
 },
 {
  "name": " Amir Ali",
  "id": "HOQ-9243-2023"
 },
 {
  "name": " Ali Mohd Ali",
  "id": "DVW-6606-2022"
 },
 {
  "name": " Ahmed M. Ali",
  "id": "CCN-1653-2022"
 },
 {
  "name": " Ahmad Ali",
  "id": "HPQ-7633-2023"
 },
 {
  "name": " Agha Shah Ali",
  "id": "HCQ-4262-2022"
 },
 {
  "name": " A. M. Ali",
  "id": "HNN-5885-2023"
 },
 {
  "name": " Muhammad Adeel Aleem",
  "id": "DSD-0924-2022"
 },
 {
  "name": " Aamir Alaud Din",
  "id": "ICI-0969-2023"
 },
 {
  "name": " Wasim Alamgir",
  "id": "EMI-5888-2022"
 },
 {
  "name": " N. Alamgir",
  "id": "CAV-5990-2022"
 },
 {
  "name": " Noor Alam",
  "id": "GYV-6375-2022"
 },
 {
  "name": " Mehmood Alam",
  "id": "GRG-2290-2022"
 },
 {
  "name": " Usman Akram",
  "id": "GQJ-5673-2022"
 },
 {
  "name": " Ramsha Akram",
  "id": "CBT-7195-2022"
 },
 {
  "name": " Javaria Akram",
  "id": "CBS-8844-2022"
 },
 {
  "name": " Farooq Akram",
  "id": "HOR-0877-2023"
 },
 {
  "name": " Farooq Akram",
  "id": "ABE-8260-2021"
 },
 {
  "name": " Dr. Safia Akram",
  "id": "HHM-1942-2022"
 },
 {
  "name": " Anum Akram",
  "id": "CBC-9828-2022"
 },
 {
  "name": " Shehnaz Akhter",
  "id": "W-9910-2019"
 },
 {
  "name": " Malik Naveed Akhter",
  "id": "CCH-6290-2022"
 },
 {
  "name": " Zubaa Akhtar",
  "id": "AAP-8433-2021"
 },
 {
  "name": " Tehseen Akhtar",
  "id": "ELH-4211-2022"
 },
 {
  "name": " Tehmina Akhtar",
  "id": "EJD-2538-2022"
 },
 {
  "name": " Shehnaz Akhtar",
  "id": "CCJ-2377-2022"
 },
 {
  "name": " Qirat Akhtar",
  "id": "EJP-8491-2022"
 },
 {
  "name": " Maham Akhtar",
  "id": "EJA-2634-2022"
 },
 {
  "name": " Imran Akhtar",
  "id": "CBR-8704-2022"
 },
 {
  "name": " Fahim Akhtar",
  "id": "CBV-8221-2022"
 },
 {
  "name": " Seema Akbar",
  "id": "EJM-9733-2022"
 },
 {
  "name": " Saddam Akbar",
  "id": "GRT-3933-2022"
 },
 {
  "name": " Muhammad Naeem Akbar",
  "id": "EJI-4235-2022"
 },
 {
  "name": " Fahad Akbar",
  "id": "EMC-3173-2022"
 },
 {
  "name": " Syed Ali Akash",
  "id": "GMA-9654-2022"
 },
 {
  "name": " Iqra Aitbar",
  "id": "EJF-2467-2022"
 },
 {
  "name": " Muhammad Tayyab Ahsan",
  "id": "AAD-9558-2022"
 },
 {
  "name": " Muhammad Hamza Ahsan",
  "id": "IAX-1610-2023"
 },
 {
  "name": " Muhammad Ahsan",
  "id": "H-8635-2012"
 },
 {
  "name": " Faaiz Ahsan",
  "id": "CAU-5756-2022"
 },
 {
  "name": " Waqas Ahmed",
  "id": "HPJ-2026-2023"
 },
 {
  "name": " Waqas Ahmed",
  "id": "U-4937-2019"
 },
 {
  "name": " Waqar Ahmed",
  "id": "DVQ-0843-2022"
 },
 {
  "name": " Umbreen Ahmed",
  "id": "EJN-8107-2022"
 },
 {
  "name": " Touqeer Ahmed",
  "id": "AAP-2195-2021"
 },
 {
  "name": " Tahir Ahmed",
  "id": "IJL-1577-2023"
 },
 {
  "name": " Shanzay Ahmed",
  "id": "GRA-7724-2022"
 },
 {
  "name": " Shakeel Ahmed",
  "id": "HHJ-4158-2022"
 },
 {
  "name": " Shahzad Ahmed",
  "id": "AAT-4583-2020"
 },
 {
  "name": " Sarfraz Ahmed",
  "id": "EJQ-6764-2022"
 },
 {
  "name": " Rameen Ayub Naveed Ahmed",
  "id": "IJR-6103-2023"
 },
 {
  "name": " Nisar Ahmed",
  "id": "GBB-8380-2022"
 },
 {
  "name": " Naveed Ahmed",
  "id": "CCK-4674-2022"
 },
 {
  "name": " Nasir M. Ahmed",
  "id": "IIU-0472-2023"
 },
 {
  "name": " Muhammad Ozair Ahmed",
  "id": "EJD-7013-2022"
 },
 {
  "name": " Moneeba Ahmed",
  "id": "CBZ-0042-2022"
 },
 {
  "name": " Mehreen Ahmed",
  "id": "EJI-7969-2022"
 },
 {
  "name": " Mehreen Ahmed",
  "id": "FZC-0886-2022"
 },
 {
  "name": " Mehreen Ahmed",
  "id": "HWQ-5341-2023"
 },
 {
  "name": " Marghoob Ahmed",
  "id": "HDO-9812-2022"
 },
 {
  "name": " Khurshid Ahmed",
  "id": "FYD-2799-2022"
 },
 {
  "name": " Fawad Ahmed",
  "id": "EKN-2997-2022"
 },
 {
  "name": " Bilal A. Ahmed",
  "id": "GWN-3001-2022"
 },
 {
  "name": " Ayyesha K. Ahmed",
  "id": "EJQ-3422-2022"
 },
 {
  "name": " Ather Maqsood Ahmed",
  "id": "EJD-7953-2022"
 },
 {
  "name": " Arshan Ahmed",
  "id": "HDP-4437-2022"
 },
 {
  "name": " Aqeel Ahmed",
  "id": "EJH-0486-2022"
 },
 {
  "name": " Anwar Saeed Ahmed",
  "id": "HGF-5655-2022"
 },
 {
  "name": " Anwaar Ahmed",
  "id": "EJK-8482-2022"
 },
 {
  "name": " Ali Ahmed",
  "id": "CAS-0612-2022"
 },
 {
  "name": " Affan Ahmed",
  "id": "HKZ-6732-2023"
 },
 {
  "name": " Adeel Ahmed",
  "id": "HGL-0618-2022"
 },
 {
  "name": " Absar Ahmed",
  "id": "EJX-8231-2022"
 },
 {
  "name": " Shoab Ahmed Khan",
  "id": "GNE-7797-2022"
 },
 {
  "name": " Waqas Ahmad",
  "id": "FZM-0743-2022"
 },
 {
  "name": " Tahir Ahmad",
  "id": "HOH-0348-2023"
 },
 {
  "name": " Tahir Ahmad",
  "id": "HTS-4718-2023"
 },
 {
  "name": " Syed Sulman A. Ahmad",
  "id": "DUK-7112-2022"
 },
 {
  "name": " Shamraiz Ahmad",
  "id": "AAY-2570-2021"
 },
 {
  "name": " Shakil Ahmad",
  "id": "CAQ-8350-2022"
 },
 {
  "name": " Shahzor Ahmad",
  "id": "HNN-6375-2023"
 },
 {
  "name": " Saleem Ahmad",
  "id": "CAZ-5636-2022"
 },
 {
  "name": " Saba Ahmad",
  "id": "EJO-2900-2022"
 },
 {
  "name": " Rizwan Ahmad",
  "id": "AAM-8784-2020"
 },
 {
  "name": " Rabia Ahmad",
  "id": "AAV-8975-2020"
 },
 {
  "name": " Qazi Nabeel Ahmad",
  "id": "HOI-0951-2023"
 },
 {
  "name": " Noman Ahmad",
  "id": "AAQ-9166-2021"
 },
 {
  "name": " Nasir Mahmood Ahmad",
  "id": "AAE-3487-2020"
 },
 {
  "name": " Muneeza Ahmad",
  "id": "CAO-4547-2022"
 },
 {
  "name": " Muhammad W. Ahmad",
  "id": "EJH-8839-2022"
 },
 {
  "name": " Muhammad Kamal Ahmad",
  "id": "CBY-7134-2022"
 },
 {
  "name": " Muhammad Ahmad",
  "id": "GAH-9945-2022"
 },
 {
  "name": " Muhammad Ahmad",
  "id": "GBK-3328-2022"
 },
 {
  "name": " Monib Ahmad",
  "id": "EKN-9978-2022"
 },
 {
  "name": " Momina Ahmad",
  "id": "EMA-8424-2022"
 },
 {
  "name": " Mohaira Ahmad",
  "id": "AAZ-3681-2020"
 },
 {
  "name": " Mian Ilyas Ahmad",
  "id": "DTE-3822-2022"
 },
 {
  "name": " Junaid Ahmad",
  "id": "DUW-5186-2022"
 },
 {
  "name": " Jawad Ahmad",
  "id": "AEU-4633-2022"
 },
 {
  "name": " Iftikhar Ahmad",
  "id": "DTX-6992-2022"
 },
 {
  "name": " Iftikhar Ahmad",
  "id": "HLJ-3399-2023"
 },
 {
  "name": " Hafiz Ali Ahmad",
  "id": "HVJ-9387-2023"
 },
 {
  "name": " Burhan Ahmad",
  "id": "CBP-3653-2022"
 },
 {
  "name": " Attiq Ahmad",
  "id": "EKQ-8405-2022"
 },
 {
  "name": " Arsalan Ahmad",
  "id": "EKJ-5311-2022"
 },
 {
  "name": " Arsalan Ahmad",
  "id": "HUC-5549-2023"
 },
 {
  "name": " A. Ahad",
  "id": "CBQ-5156-2022"
 },
 {
  "name": " Mujtaba Hassan Agha",
  "id": "AAW-8627-2020"
 },
 {
  "name": " Osama Mohammed Afzal",
  "id": "IIW-6174-2023"
 },
 {
  "name": " Hammad Afzal",
  "id": "R-6584-2018"
 },
 {
  "name": " Erum Afzal",
  "id": "CAQ-6580-2022"
 },
 {
  "name": " Anum Aftab",
  "id": "CBN-5895-2022"
 },
 {
  "name": " Saadia Afridi",
  "id": "GMC-5703-2022"
 },
 {
  "name": " Sher Afraz",
  "id": "GXI-4077-2022"
 },
 {
  "name": " Muhammad Adnan",
  "id": "AGK-1034-2022"
 },
 {
  "name": " Fazal Adnan",
  "id": "FYR-1291-2022"
 },
 {
  "name": " Sidra Adil",
  "id": "EJL-4071-2022"
 },
 {
  "name": " Iftikhar Hussain Adil",
  "id": "DST-9879-2022"
 },
 {
  "name": " Muhammad Adeel",
  "id": "GVE-4414-2022"
 },
 {
  "name": " Mahnoor Abrar",
  "id": "GMJ-4177-2022"
 },
 {
  "name": " Zubia Abid",
  "id": "CAO-2915-2022"
 },
 {
  "name": " Irfan Abid",
  "id": "CBS-0824-2022"
 },
 {
  "name": " F. Abid",
  "id": "CAK-9200-2022"
 },
 {
  "name": " Bilal Abid",
  "id": "GNE-7608-2022"
 },
 {
  "name": " Ammara Abid",
  "id": "GLW-2243-2022"
 },
 {
  "name": " Uzair Abdullah",
  "id": "EJI-4677-2022"
 },
 {
  "name": " Sayed Abdullah",
  "id": "IJS-2546-2023"
 },
 {
  "name": " B. Abdullah",
  "id": "DUL-0251-2022"
 },
 {
  "name": " Ali Abdullah",
  "id": "CAK-9235-2022"
 },
 {
  "name": " Muzzamil Abbasi",
  "id": "GMN-8297-2022"
 },
 {
  "name": " Kamran Abbasi",
  "id": "EJA-0116-2022"
 },
 {
  "name": " Hassam Abbasi",
  "id": "EJS-4272-2022"
 },
 {
  "name": " Anjum Mustafa Khan Abbasi",
  "id": "IIS-3620-2023"
 },
 {
  "name": " Amna Didar Abbasi",
  "id": "EJA-6940-2022"
 },
 {
  "name": " Shah Abbas",
  "id": "HDO-3573-2022"
 },
 {
  "name": " S. R. Abbas",
  "id": "EJC-3285-2022"
 },
 {
  "name": " Qamar Abbas",
  "id": "AAR-3256-2021"
 },
 {
  "name": " Qamar Abbas",
  "id": "HLP-1885-2023"
 },
 {
  "name": " Muhammad W. Abbas",
  "id": "CAK-4615-2022"
 },
 {
  "name": " Muhammad Asad Abbas",
  "id": "DTM-4359-2022"
 },
 {
  "name": " Laraib Abbas",
  "id": "CBG-4457-2022"
 },
 {
  "name": " Haider Abbas",
  "id": "G-1077-2014"
 },
 {
  "name": " Haider Abbas",
  "id": "ABB-1219-2021"
 },
 {
  "name": " Faisal Abbas",
  "id": "L-6052-2016"
 },
 {
  "name": " Asad Abbas",
  "id": "HVJ-0699-2023"
 },
 {
  "name": " Akhtar Abbas",
  "id": "DUC-5768-2022"
 },
 {
  "name": " Sanam Aamir",
  "id": "GRK-7161-2022"
 },
 {
  "name": " Erum Aamir",
  "id": "HLJ-6215-2023"
 },
 {
  "name": " Muhammad Aamir Cheema",
  "id": "DII-6335-2022"
 },
 {
  "name": " FARKHANDA AFZAL",
  "id": "AAJ-4256-2020"
 },
 {
  "name": " Azad A. Siddiqui",
  "id": "DRR-6286-2022"
 },
 {
  "name": " Shamim A. Qureshi",
  "id": "GYZ-5665-2022"
 }
]